[
	{
		"ID": 107832,
		"stage_BattleStage": 221032101,
		"unit_UnitUnit": 3830008,
		"money": 0,
		"initial_coordinate_x": 6,
		"initial_coordinate_y": 1,
		"reinforcement_BattleReinforcement": 0,
		"initial_direction": 0.0,
		"ai_move_group": 0,
		"ai_target_move_x": -1,
		"ai_target_move_y": -1,
		"ai_skill_function": "",
		"ai_attack": "0.0",
		"ai_move": "0.0",
		"ai_heal": "",
		"ai_skill": "",
		"ai_use": "IF(1 == 1, USESKILL(100000381), 0)",
		"skill_group_id": 23209,
		"gear_GearGear": 80029,
		"gear_rank": 10,
		"proficiency_UnitProficiency": 1,
		"level": 100,
		"hp": 99999,
		"strength": 100,
		"vitality": 116,
		"intelligence": 190,
		"mind": 134,
		"agility": 147,
		"dexterity": 154,
		"lucky": 80,
		"parameter_table_BattleEnemyParameterTable": 0,
		"parameter_deviation_table_BattleEnemyParameterDeviationTable": 0,
		"acquire_skill_group_id": 0,
		"level_correction": 0,
		"group_id": 0,
		"ai_script_id_BattleAIScript": 0
	},
	{
		"ID": 107833,
		"stage_BattleStage": 221032101,
		"unit_UnitUnit": 3830009,
		"money": 0,
		"initial_coordinate_x": 1,
		"initial_coordinate_y": 2,
		"reinforcement_BattleReinforcement": 0,
		"initial_direction": 90.0,
		"ai_move_group": 0,
		"ai_target_move_x": -1,
		"ai_target_move_y": -1,
		"ai_skill_function": "",
		"ai_attack": "IF(panel_move_distance <= 4, 1, 0)",
		"ai_move": "",
		"ai_heal": "",
		"ai_skill": "",
		"ai_use": "",
		"skill_group_id": 23210,
		"gear_GearGear": 80029,
		"gear_rank": 10,
		"proficiency_UnitProficiency": 1,
		"level": 90,
		"hp": 9999,
		"strength": 100,
		"vitality": 116,
		"intelligence": 190,
		"mind": 134,
		"agility": 146,
		"dexterity": 150,
		"lucky": 70,
		"parameter_table_BattleEnemyParameterTable": 0,
		"parameter_deviation_table_BattleEnemyParameterDeviationTable": 0,
		"acquire_skill_group_id": 0,
		"level_correction": 0,
		"group_id": 0,
		"ai_script_id_BattleAIScript": 0
	},
	{
		"ID": 107834,
		"stage_BattleStage": 221032101,
		"unit_UnitUnit": 3830009,
		"money": 0,
		"initial_coordinate_x": 1,
		"initial_coordinate_y": 8,
		"reinforcement_BattleReinforcement": 0,
		"initial_direction": 90.0,
		"ai_move_group": 0,
		"ai_target_move_x": -1,
		"ai_target_move_y": -1,
		"ai_skill_function": "",
		"ai_attack": "IF(panel_move_distance <= 4, 1, 0)",
		"ai_move": "",
		"ai_heal": "",
		"ai_skill": "",
		"ai_use": "",
		"skill_group_id": 23210,
		"gear_GearGear": 80029,
		"gear_rank": 10,
		"proficiency_UnitProficiency": 1,
		"level": 90,
		"hp": 9999,
		"strength": 100,
		"vitality": 116,
		"intelligence": 190,
		"mind": 134,
		"agility": 146,
		"dexterity": 150,
		"lucky": 70,
		"parameter_table_BattleEnemyParameterTable": 0,
		"parameter_deviation_table_BattleEnemyParameterDeviationTable": 0,
		"acquire_skill_group_id": 0,
		"level_correction": 0,
		"group_id": 0,
		"ai_script_id_BattleAIScript": 0
	},
	{
		"ID": 107835,
		"stage_BattleStage": 221032101,
		"unit_UnitUnit": 3830009,
		"money": 0,
		"initial_coordinate_x": 11,
		"initial_coordinate_y": 1,
		"reinforcement_BattleReinforcement": 0,
		"initial_direction": 270.0,
		"ai_move_group": 0,
		"ai_target_move_x": -1,
		"ai_target_move_y": -1,
		"ai_skill_function": "",
		"ai_attack": "IF(panel_move_distance <= 4, 1, 0)",
		"ai_move": "",
		"ai_heal": "",
		"ai_skill": "",
		"ai_use": "",
		"skill_group_id": 23210,
		"gear_GearGear": 80029,
		"gear_rank": 10,
		"proficiency_UnitProficiency": 1,
		"level": 90,
		"hp": 9999,
		"strength": 100,
		"vitality": 116,
		"intelligence": 190,
		"mind": 134,
		"agility": 146,
		"dexterity": 150,
		"lucky": 70,
		"parameter_table_BattleEnemyParameterTable": 0,
		"parameter_deviation_table_BattleEnemyParameterDeviationTable": 0,
		"acquire_skill_group_id": 0,
		"level_correction": 0,
		"group_id": 0,
		"ai_script_id_BattleAIScript": 0
	},
	{
		"ID": 107836,
		"stage_BattleStage": 221032101,
		"unit_UnitUnit": 3830009,
		"money": 0,
		"initial_coordinate_x": 12,
		"initial_coordinate_y": 4,
		"reinforcement_BattleReinforcement": 0,
		"initial_direction": 270.0,
		"ai_move_group": 0,
		"ai_target_move_x": -1,
		"ai_target_move_y": -1,
		"ai_skill_function": "",
		"ai_attack": "IF(panel_move_distance <= 4, 1, 0)",
		"ai_move": "",
		"ai_heal": "",
		"ai_skill": "",
		"ai_use": "",
		"skill_group_id": 23210,
		"gear_GearGear": 80029,
		"gear_rank": 10,
		"proficiency_UnitProficiency": 1,
		"level": 90,
		"hp": 9999,
		"strength": 100,
		"vitality": 116,
		"intelligence": 190,
		"mind": 134,
		"agility": 146,
		"dexterity": 150,
		"lucky": 70,
		"parameter_table_BattleEnemyParameterTable": 0,
		"parameter_deviation_table_BattleEnemyParameterDeviationTable": 0,
		"acquire_skill_group_id": 0,
		"level_correction": 0,
		"group_id": 0,
		"ai_script_id_BattleAIScript": 0
	},
	{
		"ID": 107837,
		"stage_BattleStage": 221032101,
		"unit_UnitUnit": 3830009,
		"money": 0,
		"initial_coordinate_x": 12,
		"initial_coordinate_y": 8,
		"reinforcement_BattleReinforcement": 0,
		"initial_direction": 270.0,
		"ai_move_group": 0,
		"ai_target_move_x": -1,
		"ai_target_move_y": -1,
		"ai_skill_function": "",
		"ai_attack": "IF(panel_move_distance <= 4, 1, 0)",
		"ai_move": "",
		"ai_heal": "",
		"ai_skill": "",
		"ai_use": "",
		"skill_group_id": 23210,
		"gear_GearGear": 80029,
		"gear_rank": 10,
		"proficiency_UnitProficiency": 1,
		"level": 90,
		"hp": 9999,
		"strength": 100,
		"vitality": 116,
		"intelligence": 190,
		"mind": 134,
		"agility": 146,
		"dexterity": 150,
		"lucky": 70,
		"parameter_table_BattleEnemyParameterTable": 0,
		"parameter_deviation_table_BattleEnemyParameterDeviationTable": 0,
		"acquire_skill_group_id": 0,
		"level_correction": 0,
		"group_id": 0,
		"ai_script_id_BattleAIScript": 0
	}
]