[
	{
		"ID": 17832,
		"stage_BattleStage": 241007020,
		"unit_UnitUnit": 820003,
		"money": 275,
		"initial_coordinate_x": 3,
		"initial_coordinate_y": 6,
		"reinforcement_BattleReinforcement": 0,
		"initial_direction": 180.0,
		"ai_move_group": 0,
		"ai_target_move_x": -1,
		"ai_target_move_y": -1,
		"ai_skill_function": "",
		"ai_attack": "",
		"ai_move": "",
		"ai_heal": "",
		"ai_skill": "",
		"ai_use": "",
		"skill_group_id": 2,
		"gear_GearGear": 24004,
		"gear_rank": 1,
		"proficiency_UnitProficiency": 4,
		"level": 55,
		"hp": 84,
		"strength": 58,
		"vitality": 66,
		"intelligence": 1,
		"mind": 16,
		"agility": 27,
		"dexterity": 44,
		"lucky": 9,
		"parameter_table_BattleEnemyParameterTable": 0,
		"parameter_deviation_table_BattleEnemyParameterDeviationTable": 0,
		"acquire_skill_group_id": 0,
		"level_correction": 0,
		"group_id": 0,
		"ai_script_id_BattleAIScript": 0
	},
	{
		"ID": 17833,
		"stage_BattleStage": 241007020,
		"unit_UnitUnit": 820003,
		"money": 280,
		"initial_coordinate_x": 2,
		"initial_coordinate_y": 7,
		"reinforcement_BattleReinforcement": 0,
		"initial_direction": 180.0,
		"ai_move_group": 0,
		"ai_target_move_x": -1,
		"ai_target_move_y": -1,
		"ai_skill_function": "",
		"ai_attack": "",
		"ai_move": "",
		"ai_heal": "",
		"ai_skill": "",
		"ai_use": "",
		"skill_group_id": 3,
		"gear_GearGear": 24004,
		"gear_rank": 1,
		"proficiency_UnitProficiency": 4,
		"level": 56,
		"hp": 85,
		"strength": 59,
		"vitality": 67,
		"intelligence": 1,
		"mind": 16,
		"agility": 27,
		"dexterity": 44,
		"lucky": 9,
		"parameter_table_BattleEnemyParameterTable": 0,
		"parameter_deviation_table_BattleEnemyParameterDeviationTable": 0,
		"acquire_skill_group_id": 0,
		"level_correction": 0,
		"group_id": 0,
		"ai_script_id_BattleAIScript": 0
	},
	{
		"ID": 17834,
		"stage_BattleStage": 241007020,
		"unit_UnitUnit": 820003,
		"money": 280,
		"initial_coordinate_x": 4,
		"initial_coordinate_y": 7,
		"reinforcement_BattleReinforcement": 0,
		"initial_direction": 180.0,
		"ai_move_group": 0,
		"ai_target_move_x": -1,
		"ai_target_move_y": -1,
		"ai_skill_function": "",
		"ai_attack": "",
		"ai_move": "",
		"ai_heal": "",
		"ai_skill": "",
		"ai_use": "",
		"skill_group_id": 3,
		"gear_GearGear": 24004,
		"gear_rank": 1,
		"proficiency_UnitProficiency": 4,
		"level": 56,
		"hp": 85,
		"strength": 59,
		"vitality": 67,
		"intelligence": 1,
		"mind": 16,
		"agility": 27,
		"dexterity": 44,
		"lucky": 9,
		"parameter_table_BattleEnemyParameterTable": 0,
		"parameter_deviation_table_BattleEnemyParameterDeviationTable": 0,
		"acquire_skill_group_id": 0,
		"level_correction": 0,
		"group_id": 0,
		"ai_script_id_BattleAIScript": 0
	},
	{
		"ID": 17835,
		"stage_BattleStage": 241007020,
		"unit_UnitUnit": 840004,
		"money": 270,
		"initial_coordinate_x": 6,
		"initial_coordinate_y": 6,
		"reinforcement_BattleReinforcement": 0,
		"initial_direction": 270.0,
		"ai_move_group": 0,
		"ai_target_move_x": -1,
		"ai_target_move_y": -1,
		"ai_skill_function": "",
		"ai_attack": "",
		"ai_move": "",
		"ai_heal": "",
		"ai_skill": "",
		"ai_use": "",
		"skill_group_id": 3,
		"gear_GearGear": 42002,
		"gear_rank": 1,
		"proficiency_UnitProficiency": 2,
		"level": 54,
		"hp": 68,
		"strength": 47,
		"vitality": 39,
		"intelligence": 1,
		"mind": 30,
		"agility": 38,
		"dexterity": 60,
		"lucky": 9,
		"parameter_table_BattleEnemyParameterTable": 0,
		"parameter_deviation_table_BattleEnemyParameterDeviationTable": 0,
		"acquire_skill_group_id": 0,
		"level_correction": 0,
		"group_id": 0,
		"ai_script_id_BattleAIScript": 0
	},
	{
		"ID": 17836,
		"stage_BattleStage": 241007020,
		"unit_UnitUnit": 840004,
		"money": 270,
		"initial_coordinate_x": 6,
		"initial_coordinate_y": 4,
		"reinforcement_BattleReinforcement": 0,
		"initial_direction": 270.0,
		"ai_move_group": 0,
		"ai_target_move_x": -1,
		"ai_target_move_y": -1,
		"ai_skill_function": "",
		"ai_attack": "",
		"ai_move": "",
		"ai_heal": "",
		"ai_skill": "",
		"ai_use": "",
		"skill_group_id": 3,
		"gear_GearGear": 42002,
		"gear_rank": 1,
		"proficiency_UnitProficiency": 2,
		"level": 54,
		"hp": 68,
		"strength": 47,
		"vitality": 39,
		"intelligence": 1,
		"mind": 30,
		"agility": 38,
		"dexterity": 60,
		"lucky": 9,
		"parameter_table_BattleEnemyParameterTable": 0,
		"parameter_deviation_table_BattleEnemyParameterDeviationTable": 0,
		"acquire_skill_group_id": 0,
		"level_correction": 0,
		"group_id": 0,
		"ai_script_id_BattleAIScript": 0
	},
	{
		"ID": 17837,
		"stage_BattleStage": 241007020,
		"unit_UnitUnit": 840004,
		"money": 270,
		"initial_coordinate_x": 6,
		"initial_coordinate_y": 2,
		"reinforcement_BattleReinforcement": 0,
		"initial_direction": 270.0,
		"ai_move_group": 0,
		"ai_target_move_x": -1,
		"ai_target_move_y": -1,
		"ai_skill_function": "",
		"ai_attack": "",
		"ai_move": "",
		"ai_heal": "",
		"ai_skill": "",
		"ai_use": "",
		"skill_group_id": 3,
		"gear_GearGear": 42002,
		"gear_rank": 1,
		"proficiency_UnitProficiency": 2,
		"level": 54,
		"hp": 68,
		"strength": 47,
		"vitality": 39,
		"intelligence": 1,
		"mind": 30,
		"agility": 38,
		"dexterity": 60,
		"lucky": 9,
		"parameter_table_BattleEnemyParameterTable": 0,
		"parameter_deviation_table_BattleEnemyParameterDeviationTable": 0,
		"acquire_skill_group_id": 0,
		"level_correction": 0,
		"group_id": 0,
		"ai_script_id_BattleAIScript": 0
	},
	{
		"ID": 17838,
		"stage_BattleStage": 241007020,
		"unit_UnitUnit": 840004,
		"money": 270,
		"initial_coordinate_x": 5,
		"initial_coordinate_y": 1,
		"reinforcement_BattleReinforcement": 0,
		"initial_direction": 0.0,
		"ai_move_group": 0,
		"ai_target_move_x": -1,
		"ai_target_move_y": -1,
		"ai_skill_function": "",
		"ai_attack": "",
		"ai_move": "",
		"ai_heal": "",
		"ai_skill": "",
		"ai_use": "",
		"skill_group_id": 3,
		"gear_GearGear": 42002,
		"gear_rank": 1,
		"proficiency_UnitProficiency": 2,
		"level": 54,
		"hp": 68,
		"strength": 47,
		"vitality": 39,
		"intelligence": 1,
		"mind": 30,
		"agility": 38,
		"dexterity": 60,
		"lucky": 9,
		"parameter_table_BattleEnemyParameterTable": 0,
		"parameter_deviation_table_BattleEnemyParameterDeviationTable": 0,
		"acquire_skill_group_id": 0,
		"level_correction": 0,
		"group_id": 0,
		"ai_script_id_BattleAIScript": 0
	},
	{
		"ID": 17839,
		"stage_BattleStage": 241007020,
		"unit_UnitUnit": 840004,
		"money": 270,
		"initial_coordinate_x": 3,
		"initial_coordinate_y": 1,
		"reinforcement_BattleReinforcement": 0,
		"initial_direction": 0.0,
		"ai_move_group": 0,
		"ai_target_move_x": -1,
		"ai_target_move_y": -1,
		"ai_skill_function": "",
		"ai_attack": "",
		"ai_move": "",
		"ai_heal": "",
		"ai_skill": "",
		"ai_use": "",
		"skill_group_id": 3,
		"gear_GearGear": 42002,
		"gear_rank": 1,
		"proficiency_UnitProficiency": 2,
		"level": 54,
		"hp": 68,
		"strength": 47,
		"vitality": 39,
		"intelligence": 1,
		"mind": 30,
		"agility": 38,
		"dexterity": 60,
		"lucky": 9,
		"parameter_table_BattleEnemyParameterTable": 0,
		"parameter_deviation_table_BattleEnemyParameterDeviationTable": 0,
		"acquire_skill_group_id": 0,
		"level_correction": 0,
		"group_id": 0,
		"ai_script_id_BattleAIScript": 0
	},
	{
		"ID": 17840,
		"stage_BattleStage": 241007020,
		"unit_UnitUnit": 840004,
		"money": 270,
		"initial_coordinate_x": 1,
		"initial_coordinate_y": 1,
		"reinforcement_BattleReinforcement": 21,
		"initial_direction": 0.0,
		"ai_move_group": 0,
		"ai_target_move_x": -1,
		"ai_target_move_y": -1,
		"ai_skill_function": "",
		"ai_attack": "",
		"ai_move": "",
		"ai_heal": "",
		"ai_skill": "",
		"ai_use": "",
		"skill_group_id": 3,
		"gear_GearGear": 42002,
		"gear_rank": 1,
		"proficiency_UnitProficiency": 2,
		"level": 54,
		"hp": 68,
		"strength": 47,
		"vitality": 39,
		"intelligence": 1,
		"mind": 30,
		"agility": 38,
		"dexterity": 60,
		"lucky": 9,
		"parameter_table_BattleEnemyParameterTable": 0,
		"parameter_deviation_table_BattleEnemyParameterDeviationTable": 0,
		"acquire_skill_group_id": 0,
		"level_correction": 0,
		"group_id": 0,
		"ai_script_id_BattleAIScript": 0
	},
	{
		"ID": 17841,
		"stage_BattleStage": 241007020,
		"unit_UnitUnit": 840004,
		"money": 275,
		"initial_coordinate_x": 1,
		"initial_coordinate_y": 8,
		"reinforcement_BattleReinforcement": 2,
		"initial_direction": 180.0,
		"ai_move_group": 0,
		"ai_target_move_x": -1,
		"ai_target_move_y": -1,
		"ai_skill_function": "",
		"ai_attack": "",
		"ai_move": "0.0",
		"ai_heal": "",
		"ai_skill": "",
		"ai_use": "",
		"skill_group_id": 3,
		"gear_GearGear": 42002,
		"gear_rank": 1,
		"proficiency_UnitProficiency": 2,
		"level": 55,
		"hp": 69,
		"strength": 47,
		"vitality": 40,
		"intelligence": 1,
		"mind": 31,
		"agility": 39,
		"dexterity": 61,
		"lucky": 9,
		"parameter_table_BattleEnemyParameterTable": 0,
		"parameter_deviation_table_BattleEnemyParameterDeviationTable": 0,
		"acquire_skill_group_id": 0,
		"level_correction": 0,
		"group_id": 0,
		"ai_script_id_BattleAIScript": 0
	},
	{
		"ID": 17842,
		"stage_BattleStage": 241007020,
		"unit_UnitUnit": 810004,
		"money": 275,
		"initial_coordinate_x": 3,
		"initial_coordinate_y": 8,
		"reinforcement_BattleReinforcement": 2,
		"initial_direction": 180.0,
		"ai_move_group": 0,
		"ai_target_move_x": -1,
		"ai_target_move_y": -1,
		"ai_skill_function": "",
		"ai_attack": "",
		"ai_move": "",
		"ai_heal": "",
		"ai_skill": "",
		"ai_use": "",
		"skill_group_id": 3,
		"gear_GearGear": 13001,
		"gear_rank": 1,
		"proficiency_UnitProficiency": 3,
		"level": 55,
		"hp": 72,
		"strength": 50,
		"vitality": 41,
		"intelligence": 1,
		"mind": 31,
		"agility": 47,
		"dexterity": 53,
		"lucky": 9,
		"parameter_table_BattleEnemyParameterTable": 0,
		"parameter_deviation_table_BattleEnemyParameterDeviationTable": 0,
		"acquire_skill_group_id": 0,
		"level_correction": 0,
		"group_id": 0,
		"ai_script_id_BattleAIScript": 0
	},
	{
		"ID": 17843,
		"stage_BattleStage": 241007020,
		"unit_UnitUnit": 840004,
		"money": 275,
		"initial_coordinate_x": 5,
		"initial_coordinate_y": 8,
		"reinforcement_BattleReinforcement": 2,
		"initial_direction": 180.0,
		"ai_move_group": 0,
		"ai_target_move_x": -1,
		"ai_target_move_y": -1,
		"ai_skill_function": "",
		"ai_attack": "",
		"ai_move": "0.0",
		"ai_heal": "",
		"ai_skill": "",
		"ai_use": "",
		"skill_group_id": 3,
		"gear_GearGear": 42002,
		"gear_rank": 1,
		"proficiency_UnitProficiency": 2,
		"level": 55,
		"hp": 69,
		"strength": 47,
		"vitality": 40,
		"intelligence": 1,
		"mind": 31,
		"agility": 39,
		"dexterity": 61,
		"lucky": 9,
		"parameter_table_BattleEnemyParameterTable": 0,
		"parameter_deviation_table_BattleEnemyParameterDeviationTable": 0,
		"acquire_skill_group_id": 0,
		"level_correction": 0,
		"group_id": 0,
		"ai_script_id_BattleAIScript": 0
	},
	{
		"ID": 17844,
		"stage_BattleStage": 241007020,
		"unit_UnitUnit": 810004,
		"money": 275,
		"initial_coordinate_x": 7,
		"initial_coordinate_y": 7,
		"reinforcement_BattleReinforcement": 3,
		"initial_direction": 270.0,
		"ai_move_group": 0,
		"ai_target_move_x": -1,
		"ai_target_move_y": -1,
		"ai_skill_function": "",
		"ai_attack": "",
		"ai_move": "",
		"ai_heal": "",
		"ai_skill": "",
		"ai_use": "",
		"skill_group_id": 2,
		"gear_GearGear": 13001,
		"gear_rank": 1,
		"proficiency_UnitProficiency": 3,
		"level": 55,
		"hp": 72,
		"strength": 50,
		"vitality": 41,
		"intelligence": 1,
		"mind": 31,
		"agility": 47,
		"dexterity": 53,
		"lucky": 9,
		"parameter_table_BattleEnemyParameterTable": 0,
		"parameter_deviation_table_BattleEnemyParameterDeviationTable": 0,
		"acquire_skill_group_id": 0,
		"level_correction": 0,
		"group_id": 0,
		"ai_script_id_BattleAIScript": 0
	},
	{
		"ID": 17845,
		"stage_BattleStage": 241007020,
		"unit_UnitUnit": 840004,
		"money": 275,
		"initial_coordinate_x": 7,
		"initial_coordinate_y": 5,
		"reinforcement_BattleReinforcement": 3,
		"initial_direction": 270.0,
		"ai_move_group": 0,
		"ai_target_move_x": -1,
		"ai_target_move_y": -1,
		"ai_skill_function": "",
		"ai_attack": "",
		"ai_move": "0.0",
		"ai_heal": "",
		"ai_skill": "",
		"ai_use": "",
		"skill_group_id": 3,
		"gear_GearGear": 42002,
		"gear_rank": 1,
		"proficiency_UnitProficiency": 2,
		"level": 55,
		"hp": 69,
		"strength": 47,
		"vitality": 40,
		"intelligence": 1,
		"mind": 31,
		"agility": 39,
		"dexterity": 61,
		"lucky": 9,
		"parameter_table_BattleEnemyParameterTable": 0,
		"parameter_deviation_table_BattleEnemyParameterDeviationTable": 0,
		"acquire_skill_group_id": 0,
		"level_correction": 0,
		"group_id": 0,
		"ai_script_id_BattleAIScript": 0
	},
	{
		"ID": 17846,
		"stage_BattleStage": 241007020,
		"unit_UnitUnit": 810004,
		"money": 275,
		"initial_coordinate_x": 7,
		"initial_coordinate_y": 3,
		"reinforcement_BattleReinforcement": 3,
		"initial_direction": 270.0,
		"ai_move_group": 0,
		"ai_target_move_x": -1,
		"ai_target_move_y": -1,
		"ai_skill_function": "",
		"ai_attack": "",
		"ai_move": "",
		"ai_heal": "",
		"ai_skill": "",
		"ai_use": "",
		"skill_group_id": 3,
		"gear_GearGear": 13001,
		"gear_rank": 1,
		"proficiency_UnitProficiency": 3,
		"level": 55,
		"hp": 72,
		"strength": 50,
		"vitality": 41,
		"intelligence": 1,
		"mind": 31,
		"agility": 47,
		"dexterity": 53,
		"lucky": 9,
		"parameter_table_BattleEnemyParameterTable": 0,
		"parameter_deviation_table_BattleEnemyParameterDeviationTable": 0,
		"acquire_skill_group_id": 0,
		"level_correction": 0,
		"group_id": 0,
		"ai_script_id_BattleAIScript": 0
	},
	{
		"ID": 17847,
		"stage_BattleStage": 241007020,
		"unit_UnitUnit": 840004,
		"money": 275,
		"initial_coordinate_x": 7,
		"initial_coordinate_y": 1,
		"reinforcement_BattleReinforcement": 21,
		"initial_direction": 270.0,
		"ai_move_group": 0,
		"ai_target_move_x": -1,
		"ai_target_move_y": -1,
		"ai_skill_function": "",
		"ai_attack": "",
		"ai_move": "0.0",
		"ai_heal": "",
		"ai_skill": "",
		"ai_use": "",
		"skill_group_id": 3,
		"gear_GearGear": 42002,
		"gear_rank": 1,
		"proficiency_UnitProficiency": 2,
		"level": 55,
		"hp": 69,
		"strength": 47,
		"vitality": 40,
		"intelligence": 1,
		"mind": 31,
		"agility": 39,
		"dexterity": 61,
		"lucky": 9,
		"parameter_table_BattleEnemyParameterTable": 0,
		"parameter_deviation_table_BattleEnemyParameterDeviationTable": 0,
		"acquire_skill_group_id": 0,
		"level_correction": 0,
		"group_id": 0,
		"ai_script_id_BattleAIScript": 0
	},
	{
		"ID": 17848,
		"stage_BattleStage": 241007020,
		"unit_UnitUnit": 830001,
		"money": 265,
		"initial_coordinate_x": 2,
		"initial_coordinate_y": 9,
		"reinforcement_BattleReinforcement": 0,
		"initial_direction": 180.0,
		"ai_move_group": 0,
		"ai_target_move_x": -1,
		"ai_target_move_y": -1,
		"ai_skill_function": "",
		"ai_attack": "",
		"ai_move": "IF(turn <=2,0,1)",
		"ai_heal": "",
		"ai_skill": "",
		"ai_use": "",
		"skill_group_id": 3,
		"gear_GearGear": 34002,
		"gear_rank": 1,
		"proficiency_UnitProficiency": 4,
		"level": 53,
		"hp": 64,
		"strength": 42,
		"vitality": 44,
		"intelligence": 12,
		"mind": 30,
		"agility": 44,
		"dexterity": 48,
		"lucky": 9,
		"parameter_table_BattleEnemyParameterTable": 0,
		"parameter_deviation_table_BattleEnemyParameterDeviationTable": 0,
		"acquire_skill_group_id": 0,
		"level_correction": 0,
		"group_id": 0,
		"ai_script_id_BattleAIScript": 0
	},
	{
		"ID": 17849,
		"stage_BattleStage": 241007020,
		"unit_UnitUnit": 830001,
		"money": 265,
		"initial_coordinate_x": 4,
		"initial_coordinate_y": 9,
		"reinforcement_BattleReinforcement": 0,
		"initial_direction": 180.0,
		"ai_move_group": 0,
		"ai_target_move_x": -1,
		"ai_target_move_y": -1,
		"ai_skill_function": "",
		"ai_attack": "",
		"ai_move": "IF(turn <=2,0,1)",
		"ai_heal": "",
		"ai_skill": "",
		"ai_use": "",
		"skill_group_id": 3,
		"gear_GearGear": 34002,
		"gear_rank": 1,
		"proficiency_UnitProficiency": 4,
		"level": 53,
		"hp": 64,
		"strength": 42,
		"vitality": 44,
		"intelligence": 12,
		"mind": 30,
		"agility": 44,
		"dexterity": 48,
		"lucky": 9,
		"parameter_table_BattleEnemyParameterTable": 0,
		"parameter_deviation_table_BattleEnemyParameterDeviationTable": 0,
		"acquire_skill_group_id": 0,
		"level_correction": 0,
		"group_id": 0,
		"ai_script_id_BattleAIScript": 0
	},
	{
		"ID": 17850,
		"stage_BattleStage": 241007020,
		"unit_UnitUnit": 820007,
		"money": 275,
		"initial_coordinate_x": 3,
		"initial_coordinate_y": 10,
		"reinforcement_BattleReinforcement": 0,
		"initial_direction": 180.0,
		"ai_move_group": 0,
		"ai_target_move_x": -1,
		"ai_target_move_y": -1,
		"ai_skill_function": "",
		"ai_attack": "",
		"ai_move": "IF(turn <=2,0,1)",
		"ai_heal": "",
		"ai_skill": "",
		"ai_use": "",
		"skill_group_id": 4,
		"gear_GearGear": 24001,
		"gear_rank": 1,
		"proficiency_UnitProficiency": 4,
		"level": 55,
		"hp": 78,
		"strength": 60,
		"vitality": 53,
		"intelligence": 2,
		"mind": 35,
		"agility": 30,
		"dexterity": 48,
		"lucky": 9,
		"parameter_table_BattleEnemyParameterTable": 0,
		"parameter_deviation_table_BattleEnemyParameterDeviationTable": 0,
		"acquire_skill_group_id": 0,
		"level_correction": 0,
		"group_id": 0,
		"ai_script_id_BattleAIScript": 0
	},
	{
		"ID": 17851,
		"stage_BattleStage": 241007020,
		"unit_UnitUnit": 830001,
		"money": 265,
		"initial_coordinate_x": 8,
		"initial_coordinate_y": 4,
		"reinforcement_BattleReinforcement": 0,
		"initial_direction": 270.0,
		"ai_move_group": 0,
		"ai_target_move_x": -1,
		"ai_target_move_y": -1,
		"ai_skill_function": "",
		"ai_attack": "",
		"ai_move": "IF(turn <=2,0,1)",
		"ai_heal": "",
		"ai_skill": "",
		"ai_use": "",
		"skill_group_id": 3,
		"gear_GearGear": 34002,
		"gear_rank": 1,
		"proficiency_UnitProficiency": 4,
		"level": 53,
		"hp": 64,
		"strength": 42,
		"vitality": 44,
		"intelligence": 12,
		"mind": 30,
		"agility": 44,
		"dexterity": 48,
		"lucky": 9,
		"parameter_table_BattleEnemyParameterTable": 0,
		"parameter_deviation_table_BattleEnemyParameterDeviationTable": 0,
		"acquire_skill_group_id": 0,
		"level_correction": 0,
		"group_id": 0,
		"ai_script_id_BattleAIScript": 0
	},
	{
		"ID": 17852,
		"stage_BattleStage": 241007020,
		"unit_UnitUnit": 830001,
		"money": 265,
		"initial_coordinate_x": 8,
		"initial_coordinate_y": 2,
		"reinforcement_BattleReinforcement": 0,
		"initial_direction": 270.0,
		"ai_move_group": 0,
		"ai_target_move_x": -1,
		"ai_target_move_y": -1,
		"ai_skill_function": "",
		"ai_attack": "",
		"ai_move": "IF(turn <=2,0,1)",
		"ai_heal": "",
		"ai_skill": "",
		"ai_use": "",
		"skill_group_id": 3,
		"gear_GearGear": 34002,
		"gear_rank": 1,
		"proficiency_UnitProficiency": 4,
		"level": 53,
		"hp": 64,
		"strength": 42,
		"vitality": 44,
		"intelligence": 12,
		"mind": 30,
		"agility": 44,
		"dexterity": 48,
		"lucky": 9,
		"parameter_table_BattleEnemyParameterTable": 0,
		"parameter_deviation_table_BattleEnemyParameterDeviationTable": 0,
		"acquire_skill_group_id": 0,
		"level_correction": 0,
		"group_id": 0,
		"ai_script_id_BattleAIScript": 0
	},
	{
		"ID": 17853,
		"stage_BattleStage": 241007020,
		"unit_UnitUnit": 820007,
		"money": 275,
		"initial_coordinate_x": 9,
		"initial_coordinate_y": 3,
		"reinforcement_BattleReinforcement": 0,
		"initial_direction": 270.0,
		"ai_move_group": 0,
		"ai_target_move_x": -1,
		"ai_target_move_y": -1,
		"ai_skill_function": "",
		"ai_attack": "",
		"ai_move": "IF(turn <=2,0,1)",
		"ai_heal": "",
		"ai_skill": "",
		"ai_use": "",
		"skill_group_id": 4,
		"gear_GearGear": 24001,
		"gear_rank": 1,
		"proficiency_UnitProficiency": 4,
		"level": 55,
		"hp": 78,
		"strength": 60,
		"vitality": 53,
		"intelligence": 2,
		"mind": 35,
		"agility": 30,
		"dexterity": 48,
		"lucky": 9,
		"parameter_table_BattleEnemyParameterTable": 0,
		"parameter_deviation_table_BattleEnemyParameterDeviationTable": 0,
		"acquire_skill_group_id": 0,
		"level_correction": 0,
		"group_id": 0,
		"ai_script_id_BattleAIScript": 0
	},
	{
		"ID": 17854,
		"stage_BattleStage": 241007020,
		"unit_UnitUnit": 802201,
		"money": 350,
		"initial_coordinate_x": 7,
		"initial_coordinate_y": 11,
		"reinforcement_BattleReinforcement": 0,
		"initial_direction": 180.0,
		"ai_move_group": 0,
		"ai_target_move_x": -1,
		"ai_target_move_y": -1,
		"ai_skill_function": "",
		"ai_attack": "IF(panel_move_distance = 0, 1, 0)",
		"ai_move": "0.0",
		"ai_heal": "",
		"ai_skill": "",
		"ai_use": "",
		"skill_group_id": 2493,
		"gear_GearGear": 80011,
		"gear_rank": 1,
		"proficiency_UnitProficiency": 1,
		"level": 70,
		"hp": 385,
		"strength": 45,
		"vitality": 40,
		"intelligence": 36,
		"mind": 84,
		"agility": 39,
		"dexterity": 50,
		"lucky": 34,
		"parameter_table_BattleEnemyParameterTable": 0,
		"parameter_deviation_table_BattleEnemyParameterDeviationTable": 0,
		"acquire_skill_group_id": 0,
		"level_correction": 0,
		"group_id": 0,
		"ai_script_id_BattleAIScript": 0
	},
	{
		"ID": 17855,
		"stage_BattleStage": 241007020,
		"unit_UnitUnit": 802201,
		"money": 350,
		"initial_coordinate_x": 11,
		"initial_coordinate_y": 7,
		"reinforcement_BattleReinforcement": 0,
		"initial_direction": 270.0,
		"ai_move_group": 0,
		"ai_target_move_x": -1,
		"ai_target_move_y": -1,
		"ai_skill_function": "",
		"ai_attack": "IF(panel_move_distance = 0, 1, 0)",
		"ai_move": "0.0",
		"ai_heal": "",
		"ai_skill": "",
		"ai_use": "",
		"skill_group_id": 2493,
		"gear_GearGear": 80011,
		"gear_rank": 1,
		"proficiency_UnitProficiency": 1,
		"level": 70,
		"hp": 395,
		"strength": 45,
		"vitality": 40,
		"intelligence": 36,
		"mind": 84,
		"agility": 39,
		"dexterity": 50,
		"lucky": 34,
		"parameter_table_BattleEnemyParameterTable": 0,
		"parameter_deviation_table_BattleEnemyParameterDeviationTable": 0,
		"acquire_skill_group_id": 0,
		"level_correction": 0,
		"group_id": 0,
		"ai_script_id_BattleAIScript": 0
	},
	{
		"ID": 17856,
		"stage_BattleStage": 241007020,
		"unit_UnitUnit": 802201,
		"money": 350,
		"initial_coordinate_x": 15,
		"initial_coordinate_y": 9,
		"reinforcement_BattleReinforcement": 0,
		"initial_direction": 270.0,
		"ai_move_group": 0,
		"ai_target_move_x": -1,
		"ai_target_move_y": -1,
		"ai_skill_function": "",
		"ai_attack": "IF(panel_move_distance = 0, 1, 0)",
		"ai_move": "0.0",
		"ai_heal": "",
		"ai_skill": "",
		"ai_use": "",
		"skill_group_id": 2493,
		"gear_GearGear": 80011,
		"gear_rank": 1,
		"proficiency_UnitProficiency": 1,
		"level": 70,
		"hp": 411,
		"strength": 46,
		"vitality": 42,
		"intelligence": 37,
		"mind": 87,
		"agility": 40,
		"dexterity": 52,
		"lucky": 35,
		"parameter_table_BattleEnemyParameterTable": 0,
		"parameter_deviation_table_BattleEnemyParameterDeviationTable": 0,
		"acquire_skill_group_id": 0,
		"level_correction": 0,
		"group_id": 0,
		"ai_script_id_BattleAIScript": 0
	},
	{
		"ID": 17857,
		"stage_BattleStage": 241007020,
		"unit_UnitUnit": 802201,
		"money": 350,
		"initial_coordinate_x": 18,
		"initial_coordinate_y": 10,
		"reinforcement_BattleReinforcement": 0,
		"initial_direction": 270.0,
		"ai_move_group": 0,
		"ai_target_move_x": -1,
		"ai_target_move_y": -1,
		"ai_skill_function": "",
		"ai_attack": "IF(panel_move_distance = 0, 1, 0)",
		"ai_move": "0.0",
		"ai_heal": "",
		"ai_skill": "",
		"ai_use": "",
		"skill_group_id": 2493,
		"gear_GearGear": 80011,
		"gear_rank": 1,
		"proficiency_UnitProficiency": 1,
		"level": 70,
		"hp": 419,
		"strength": 47,
		"vitality": 42,
		"intelligence": 37,
		"mind": 88,
		"agility": 40,
		"dexterity": 53,
		"lucky": 35,
		"parameter_table_BattleEnemyParameterTable": 0,
		"parameter_deviation_table_BattleEnemyParameterDeviationTable": 0,
		"acquire_skill_group_id": 0,
		"level_correction": 0,
		"group_id": 0,
		"ai_script_id_BattleAIScript": 0
	},
	{
		"ID": 17858,
		"stage_BattleStage": 241007020,
		"unit_UnitUnit": 810004,
		"money": 280,
		"initial_coordinate_x": 8,
		"initial_coordinate_y": 9,
		"reinforcement_BattleReinforcement": 0,
		"initial_direction": 180.0,
		"ai_move_group": 0,
		"ai_target_move_x": -1,
		"ai_target_move_y": -1,
		"ai_skill_function": "",
		"ai_attack": "IF(panel_move_distance <= 1, 1, 0)",
		"ai_move": "0.0",
		"ai_heal": "",
		"ai_skill": "",
		"ai_use": "",
		"skill_group_id": 3,
		"gear_GearGear": 13001,
		"gear_rank": 1,
		"proficiency_UnitProficiency": 3,
		"level": 56,
		"hp": 73,
		"strength": 51,
		"vitality": 41,
		"intelligence": 1,
		"mind": 31,
		"agility": 47,
		"dexterity": 54,
		"lucky": 9,
		"parameter_table_BattleEnemyParameterTable": 0,
		"parameter_deviation_table_BattleEnemyParameterDeviationTable": 0,
		"acquire_skill_group_id": 0,
		"level_correction": 0,
		"group_id": 0,
		"ai_script_id_BattleAIScript": 0
	},
	{
		"ID": 17859,
		"stage_BattleStage": 241007020,
		"unit_UnitUnit": 810004,
		"money": 280,
		"initial_coordinate_x": 9,
		"initial_coordinate_y": 8,
		"reinforcement_BattleReinforcement": 0,
		"initial_direction": 270.0,
		"ai_move_group": 0,
		"ai_target_move_x": -1,
		"ai_target_move_y": -1,
		"ai_skill_function": "",
		"ai_attack": "IF(panel_move_distance <= 1, 1, 0)",
		"ai_move": "0.0",
		"ai_heal": "",
		"ai_skill": "",
		"ai_use": "",
		"skill_group_id": 3,
		"gear_GearGear": 13001,
		"gear_rank": 1,
		"proficiency_UnitProficiency": 3,
		"level": 56,
		"hp": 73,
		"strength": 51,
		"vitality": 41,
		"intelligence": 1,
		"mind": 31,
		"agility": 47,
		"dexterity": 54,
		"lucky": 9,
		"parameter_table_BattleEnemyParameterTable": 0,
		"parameter_deviation_table_BattleEnemyParameterDeviationTable": 0,
		"acquire_skill_group_id": 0,
		"level_correction": 0,
		"group_id": 0,
		"ai_script_id_BattleAIScript": 0
	},
	{
		"ID": 17860,
		"stage_BattleStage": 241007020,
		"unit_UnitUnit": 860006,
		"money": 270,
		"initial_coordinate_x": 9,
		"initial_coordinate_y": 9,
		"reinforcement_BattleReinforcement": 0,
		"initial_direction": 270.0,
		"ai_move_group": 0,
		"ai_target_move_x": -1,
		"ai_target_move_y": -1,
		"ai_skill_function": "",
		"ai_attack": "IF(panel_move_distance <= 1, 1, 0)",
		"ai_move": "0.0",
		"ai_heal": "",
		"ai_skill": "",
		"ai_use": "",
		"skill_group_id": 592,
		"gear_GearGear": 64001,
		"gear_rank": 1,
		"proficiency_UnitProficiency": 4,
		"level": 54,
		"hp": 64,
		"strength": 6,
		"vitality": 27,
		"intelligence": 42,
		"mind": 47,
		"agility": 35,
		"dexterity": 45,
		"lucky": 9,
		"parameter_table_BattleEnemyParameterTable": 0,
		"parameter_deviation_table_BattleEnemyParameterDeviationTable": 0,
		"acquire_skill_group_id": 0,
		"level_correction": 0,
		"group_id": 0,
		"ai_script_id_BattleAIScript": 0
	},
	{
		"ID": 17861,
		"stage_BattleStage": 241007020,
		"unit_UnitUnit": 820003,
		"money": 285,
		"initial_coordinate_x": 10,
		"initial_coordinate_y": 11,
		"reinforcement_BattleReinforcement": 0,
		"initial_direction": 180.0,
		"ai_move_group": 0,
		"ai_target_move_x": -1,
		"ai_target_move_y": -1,
		"ai_skill_function": "",
		"ai_attack": "IF(panel_move_distance <= 1, 1, 0)",
		"ai_move": "0.0",
		"ai_heal": "",
		"ai_skill": "",
		"ai_use": "",
		"skill_group_id": 1,
		"gear_GearGear": 24004,
		"gear_rank": 1,
		"proficiency_UnitProficiency": 4,
		"level": 57,
		"hp": 86,
		"strength": 60,
		"vitality": 68,
		"intelligence": 1,
		"mind": 17,
		"agility": 28,
		"dexterity": 45,
		"lucky": 9,
		"parameter_table_BattleEnemyParameterTable": 0,
		"parameter_deviation_table_BattleEnemyParameterDeviationTable": 0,
		"acquire_skill_group_id": 0,
		"level_correction": 0,
		"group_id": 0,
		"ai_script_id_BattleAIScript": 0
	},
	{
		"ID": 17862,
		"stage_BattleStage": 241007020,
		"unit_UnitUnit": 820003,
		"money": 285,
		"initial_coordinate_x": 11,
		"initial_coordinate_y": 10,
		"reinforcement_BattleReinforcement": 0,
		"initial_direction": 270.0,
		"ai_move_group": 0,
		"ai_target_move_x": -1,
		"ai_target_move_y": -1,
		"ai_skill_function": "",
		"ai_attack": "IF(panel_move_distance <= 1, 1, 0)",
		"ai_move": "0.0",
		"ai_heal": "",
		"ai_skill": "",
		"ai_use": "",
		"skill_group_id": 1,
		"gear_GearGear": 24004,
		"gear_rank": 1,
		"proficiency_UnitProficiency": 4,
		"level": 57,
		"hp": 86,
		"strength": 60,
		"vitality": 68,
		"intelligence": 1,
		"mind": 17,
		"agility": 28,
		"dexterity": 45,
		"lucky": 9,
		"parameter_table_BattleEnemyParameterTable": 0,
		"parameter_deviation_table_BattleEnemyParameterDeviationTable": 0,
		"acquire_skill_group_id": 0,
		"level_correction": 0,
		"group_id": 0,
		"ai_script_id_BattleAIScript": 0
	},
	{
		"ID": 17863,
		"stage_BattleStage": 241007020,
		"unit_UnitUnit": 860006,
		"money": 275,
		"initial_coordinate_x": 11,
		"initial_coordinate_y": 11,
		"reinforcement_BattleReinforcement": 0,
		"initial_direction": 270.0,
		"ai_move_group": 0,
		"ai_target_move_x": -1,
		"ai_target_move_y": -1,
		"ai_skill_function": "",
		"ai_attack": "IF(panel_move_distance <= 1, 1, 0)",
		"ai_move": "0.0",
		"ai_heal": "",
		"ai_skill": "",
		"ai_use": "",
		"skill_group_id": 592,
		"gear_GearGear": 64001,
		"gear_rank": 1,
		"proficiency_UnitProficiency": 4,
		"level": 55,
		"hp": 65,
		"strength": 7,
		"vitality": 27,
		"intelligence": 43,
		"mind": 48,
		"agility": 36,
		"dexterity": 46,
		"lucky": 9,
		"parameter_table_BattleEnemyParameterTable": 0,
		"parameter_deviation_table_BattleEnemyParameterDeviationTable": 0,
		"acquire_skill_group_id": 0,
		"level_correction": 0,
		"group_id": 0,
		"ai_script_id_BattleAIScript": 0
	},
	{
		"ID": 17864,
		"stage_BattleStage": 241007020,
		"unit_UnitUnit": 810004,
		"money": 290,
		"initial_coordinate_x": 14,
		"initial_coordinate_y": 11,
		"reinforcement_BattleReinforcement": 0,
		"initial_direction": 270.0,
		"ai_move_group": 0,
		"ai_target_move_x": -1,
		"ai_target_move_y": -1,
		"ai_skill_function": "",
		"ai_attack": "",
		"ai_move": "0.0",
		"ai_heal": "",
		"ai_skill": "",
		"ai_use": "",
		"skill_group_id": 3,
		"gear_GearGear": 13001,
		"gear_rank": 1,
		"proficiency_UnitProficiency": 3,
		"level": 58,
		"hp": 74,
		"strength": 52,
		"vitality": 42,
		"intelligence": 1,
		"mind": 32,
		"agility": 49,
		"dexterity": 55,
		"lucky": 9,
		"parameter_table_BattleEnemyParameterTable": 0,
		"parameter_deviation_table_BattleEnemyParameterDeviationTable": 0,
		"acquire_skill_group_id": 0,
		"level_correction": 0,
		"group_id": 0,
		"ai_script_id_BattleAIScript": 0
	},
	{
		"ID": 17865,
		"stage_BattleStage": 241007020,
		"unit_UnitUnit": 810004,
		"money": 290,
		"initial_coordinate_x": 15,
		"initial_coordinate_y": 12,
		"reinforcement_BattleReinforcement": 0,
		"initial_direction": 270.0,
		"ai_move_group": 0,
		"ai_target_move_x": -1,
		"ai_target_move_y": -1,
		"ai_skill_function": "",
		"ai_attack": "",
		"ai_move": "0.0",
		"ai_heal": "",
		"ai_skill": "",
		"ai_use": "",
		"skill_group_id": 3,
		"gear_GearGear": 13001,
		"gear_rank": 1,
		"proficiency_UnitProficiency": 3,
		"level": 58,
		"hp": 74,
		"strength": 52,
		"vitality": 42,
		"intelligence": 1,
		"mind": 32,
		"agility": 49,
		"dexterity": 55,
		"lucky": 9,
		"parameter_table_BattleEnemyParameterTable": 0,
		"parameter_deviation_table_BattleEnemyParameterDeviationTable": 0,
		"acquire_skill_group_id": 0,
		"level_correction": 0,
		"group_id": 0,
		"ai_script_id_BattleAIScript": 0
	},
	{
		"ID": 17866,
		"stage_BattleStage": 241007020,
		"unit_UnitUnit": 860006,
		"money": 290,
		"initial_coordinate_x": 16,
		"initial_coordinate_y": 11,
		"reinforcement_BattleReinforcement": 0,
		"initial_direction": 270.0,
		"ai_move_group": 0,
		"ai_target_move_x": -1,
		"ai_target_move_y": -1,
		"ai_skill_function": "",
		"ai_attack": "",
		"ai_move": "0.0",
		"ai_heal": "",
		"ai_skill": "",
		"ai_use": "",
		"skill_group_id": 592,
		"gear_GearGear": 64001,
		"gear_rank": 1,
		"proficiency_UnitProficiency": 4,
		"level": 58,
		"hp": 67,
		"strength": 7,
		"vitality": 28,
		"intelligence": 45,
		"mind": 51,
		"agility": 37,
		"dexterity": 48,
		"lucky": 9,
		"parameter_table_BattleEnemyParameterTable": 0,
		"parameter_deviation_table_BattleEnemyParameterDeviationTable": 0,
		"acquire_skill_group_id": 0,
		"level_correction": 0,
		"group_id": 0,
		"ai_script_id_BattleAIScript": 0
	},
	{
		"ID": 17867,
		"stage_BattleStage": 241007020,
		"unit_UnitUnit": 810002,
		"money": 285,
		"initial_coordinate_x": 16,
		"initial_coordinate_y": 6,
		"reinforcement_BattleReinforcement": 4,
		"initial_direction": 270.0,
		"ai_move_group": 0,
		"ai_target_move_x": -1,
		"ai_target_move_y": -1,
		"ai_skill_function": "",
		"ai_attack": "",
		"ai_move": "",
		"ai_heal": "",
		"ai_skill": "",
		"ai_use": "",
		"skill_group_id": 3,
		"gear_GearGear": 13001,
		"gear_rank": 1,
		"proficiency_UnitProficiency": 3,
		"level": 57,
		"hp": 79,
		"strength": 51,
		"vitality": 44,
		"intelligence": 1,
		"mind": 26,
		"agility": 44,
		"dexterity": 48,
		"lucky": 9,
		"parameter_table_BattleEnemyParameterTable": 0,
		"parameter_deviation_table_BattleEnemyParameterDeviationTable": 0,
		"acquire_skill_group_id": 0,
		"level_correction": 0,
		"group_id": 0,
		"ai_script_id_BattleAIScript": 0
	},
	{
		"ID": 17868,
		"stage_BattleStage": 241007020,
		"unit_UnitUnit": 810002,
		"money": 285,
		"initial_coordinate_x": 16,
		"initial_coordinate_y": 5,
		"reinforcement_BattleReinforcement": 4,
		"initial_direction": 270.0,
		"ai_move_group": 0,
		"ai_target_move_x": -1,
		"ai_target_move_y": -1,
		"ai_skill_function": "",
		"ai_attack": "",
		"ai_move": "",
		"ai_heal": "",
		"ai_skill": "",
		"ai_use": "",
		"skill_group_id": 3,
		"gear_GearGear": 13001,
		"gear_rank": 1,
		"proficiency_UnitProficiency": 3,
		"level": 57,
		"hp": 79,
		"strength": 51,
		"vitality": 44,
		"intelligence": 1,
		"mind": 26,
		"agility": 44,
		"dexterity": 48,
		"lucky": 9,
		"parameter_table_BattleEnemyParameterTable": 0,
		"parameter_deviation_table_BattleEnemyParameterDeviationTable": 0,
		"acquire_skill_group_id": 0,
		"level_correction": 0,
		"group_id": 0,
		"ai_script_id_BattleAIScript": 0
	},
	{
		"ID": 17869,
		"stage_BattleStage": 241007020,
		"unit_UnitUnit": 830002,
		"money": 290,
		"initial_coordinate_x": 17,
		"initial_coordinate_y": 6,
		"reinforcement_BattleReinforcement": 5,
		"initial_direction": 270.0,
		"ai_move_group": 0,
		"ai_target_move_x": -1,
		"ai_target_move_y": -1,
		"ai_skill_function": "",
		"ai_attack": "",
		"ai_move": "",
		"ai_heal": "",
		"ai_skill": "",
		"ai_use": "",
		"skill_group_id": 1,
		"gear_GearGear": 33002,
		"gear_rank": 1,
		"proficiency_UnitProficiency": 3,
		"level": 58,
		"hp": 79,
		"strength": 54,
		"vitality": 49,
		"intelligence": 1,
		"mind": 28,
		"agility": 39,
		"dexterity": 46,
		"lucky": 9,
		"parameter_table_BattleEnemyParameterTable": 0,
		"parameter_deviation_table_BattleEnemyParameterDeviationTable": 0,
		"acquire_skill_group_id": 0,
		"level_correction": 0,
		"group_id": 0,
		"ai_script_id_BattleAIScript": 0
	},
	{
		"ID": 17870,
		"stage_BattleStage": 241007020,
		"unit_UnitUnit": 830002,
		"money": 290,
		"initial_coordinate_x": 17,
		"initial_coordinate_y": 5,
		"reinforcement_BattleReinforcement": 5,
		"initial_direction": 270.0,
		"ai_move_group": 0,
		"ai_target_move_x": -1,
		"ai_target_move_y": -1,
		"ai_skill_function": "",
		"ai_attack": "",
		"ai_move": "",
		"ai_heal": "",
		"ai_skill": "",
		"ai_use": "",
		"skill_group_id": 1,
		"gear_GearGear": 33002,
		"gear_rank": 1,
		"proficiency_UnitProficiency": 3,
		"level": 58,
		"hp": 79,
		"strength": 54,
		"vitality": 49,
		"intelligence": 1,
		"mind": 28,
		"agility": 39,
		"dexterity": 46,
		"lucky": 9,
		"parameter_table_BattleEnemyParameterTable": 0,
		"parameter_deviation_table_BattleEnemyParameterDeviationTable": 0,
		"acquire_skill_group_id": 0,
		"level_correction": 0,
		"group_id": 0,
		"ai_script_id_BattleAIScript": 0
	},
	{
		"ID": 17871,
		"stage_BattleStage": 241007020,
		"unit_UnitUnit": 810002,
		"money": 295,
		"initial_coordinate_x": 18,
		"initial_coordinate_y": 6,
		"reinforcement_BattleReinforcement": 6,
		"initial_direction": 270.0,
		"ai_move_group": 0,
		"ai_target_move_x": -1,
		"ai_target_move_y": -1,
		"ai_skill_function": "",
		"ai_attack": "",
		"ai_move": "",
		"ai_heal": "",
		"ai_skill": "",
		"ai_use": "",
		"skill_group_id": 3,
		"gear_GearGear": 13001,
		"gear_rank": 1,
		"proficiency_UnitProficiency": 3,
		"level": 59,
		"hp": 81,
		"strength": 52,
		"vitality": 45,
		"intelligence": 1,
		"mind": 27,
		"agility": 46,
		"dexterity": 49,
		"lucky": 9,
		"parameter_table_BattleEnemyParameterTable": 0,
		"parameter_deviation_table_BattleEnemyParameterDeviationTable": 0,
		"acquire_skill_group_id": 0,
		"level_correction": 0,
		"group_id": 0,
		"ai_script_id_BattleAIScript": 0
	},
	{
		"ID": 17872,
		"stage_BattleStage": 241007020,
		"unit_UnitUnit": 810002,
		"money": 295,
		"initial_coordinate_x": 18,
		"initial_coordinate_y": 5,
		"reinforcement_BattleReinforcement": 6,
		"initial_direction": 270.0,
		"ai_move_group": 0,
		"ai_target_move_x": -1,
		"ai_target_move_y": -1,
		"ai_skill_function": "",
		"ai_attack": "",
		"ai_move": "",
		"ai_heal": "",
		"ai_skill": "",
		"ai_use": "",
		"skill_group_id": 3,
		"gear_GearGear": 13001,
		"gear_rank": 1,
		"proficiency_UnitProficiency": 3,
		"level": 59,
		"hp": 81,
		"strength": 52,
		"vitality": 45,
		"intelligence": 1,
		"mind": 27,
		"agility": 46,
		"dexterity": 49,
		"lucky": 9,
		"parameter_table_BattleEnemyParameterTable": 0,
		"parameter_deviation_table_BattleEnemyParameterDeviationTable": 0,
		"acquire_skill_group_id": 0,
		"level_correction": 0,
		"group_id": 0,
		"ai_script_id_BattleAIScript": 0
	},
	{
		"ID": 17873,
		"stage_BattleStage": 241007020,
		"unit_UnitUnit": 830002,
		"money": 300,
		"initial_coordinate_x": 19,
		"initial_coordinate_y": 6,
		"reinforcement_BattleReinforcement": 7,
		"initial_direction": 270.0,
		"ai_move_group": 0,
		"ai_target_move_x": -1,
		"ai_target_move_y": -1,
		"ai_skill_function": "",
		"ai_attack": "",
		"ai_move": "",
		"ai_heal": "",
		"ai_skill": "",
		"ai_use": "",
		"skill_group_id": 2,
		"gear_GearGear": 33002,
		"gear_rank": 1,
		"proficiency_UnitProficiency": 3,
		"level": 60,
		"hp": 80,
		"strength": 56,
		"vitality": 51,
		"intelligence": 1,
		"mind": 28,
		"agility": 40,
		"dexterity": 47,
		"lucky": 9,
		"parameter_table_BattleEnemyParameterTable": 0,
		"parameter_deviation_table_BattleEnemyParameterDeviationTable": 0,
		"acquire_skill_group_id": 0,
		"level_correction": 0,
		"group_id": 0,
		"ai_script_id_BattleAIScript": 0
	},
	{
		"ID": 17874,
		"stage_BattleStage": 241007020,
		"unit_UnitUnit": 830002,
		"money": 300,
		"initial_coordinate_x": 19,
		"initial_coordinate_y": 5,
		"reinforcement_BattleReinforcement": 7,
		"initial_direction": 270.0,
		"ai_move_group": 0,
		"ai_target_move_x": -1,
		"ai_target_move_y": -1,
		"ai_skill_function": "",
		"ai_attack": "",
		"ai_move": "",
		"ai_heal": "",
		"ai_skill": "",
		"ai_use": "",
		"skill_group_id": 2,
		"gear_GearGear": 33002,
		"gear_rank": 1,
		"proficiency_UnitProficiency": 3,
		"level": 60,
		"hp": 80,
		"strength": 56,
		"vitality": 51,
		"intelligence": 1,
		"mind": 28,
		"agility": 40,
		"dexterity": 47,
		"lucky": 9,
		"parameter_table_BattleEnemyParameterTable": 0,
		"parameter_deviation_table_BattleEnemyParameterDeviationTable": 0,
		"acquire_skill_group_id": 0,
		"level_correction": 0,
		"group_id": 0,
		"ai_script_id_BattleAIScript": 0
	}
]