[
	{
		"ID": 41743,
		"stage_BattleStage": 271002136,
		"unit_UnitUnit": 840004,
		"money": 230,
		"initial_coordinate_x": 8,
		"initial_coordinate_y": 4,
		"reinforcement_BattleReinforcement": 0,
		"initial_direction": 270.0,
		"ai_move_group": 0,
		"ai_target_move_x": -1,
		"ai_target_move_y": -1,
		"ai_skill_function": "",
		"ai_attack": "",
		"ai_move": "",
		"ai_heal": "",
		"ai_skill": "",
		"ai_use": "",
		"skill_group_id": 0,
		"gear_GearGear": 41002,
		"gear_rank": 1,
		"proficiency_UnitProficiency": 1,
		"level": 46,
		"hp": 53,
		"strength": 39,
		"vitality": 38,
		"intelligence": 30,
		"mind": 30,
		"agility": 37,
		"dexterity": 42,
		"lucky": 13,
		"parameter_table_BattleEnemyParameterTable": 0,
		"parameter_deviation_table_BattleEnemyParameterDeviationTable": 0,
		"acquire_skill_group_id": 131,
		"level_correction": 0,
		"group_id": 0,
		"ai_script_id_BattleAIScript": 0
	},
	{
		"ID": 41744,
		"stage_BattleStage": 271002136,
		"unit_UnitUnit": 840004,
		"money": 230,
		"initial_coordinate_x": 8,
		"initial_coordinate_y": 3,
		"reinforcement_BattleReinforcement": 0,
		"initial_direction": 270.0,
		"ai_move_group": 0,
		"ai_target_move_x": -1,
		"ai_target_move_y": -1,
		"ai_skill_function": "",
		"ai_attack": "",
		"ai_move": "",
		"ai_heal": "",
		"ai_skill": "",
		"ai_use": "",
		"skill_group_id": 0,
		"gear_GearGear": 42001,
		"gear_rank": 1,
		"proficiency_UnitProficiency": 2,
		"level": 46,
		"hp": 55,
		"strength": 41,
		"vitality": 45,
		"intelligence": 33,
		"mind": 30,
		"agility": 41,
		"dexterity": 40,
		"lucky": 12,
		"parameter_table_BattleEnemyParameterTable": 0,
		"parameter_deviation_table_BattleEnemyParameterDeviationTable": 0,
		"acquire_skill_group_id": 131,
		"level_correction": 0,
		"group_id": 0,
		"ai_script_id_BattleAIScript": 0
	},
	{
		"ID": 41745,
		"stage_BattleStage": 271002136,
		"unit_UnitUnit": 840004,
		"money": 230,
		"initial_coordinate_x": 8,
		"initial_coordinate_y": 2,
		"reinforcement_BattleReinforcement": 0,
		"initial_direction": 270.0,
		"ai_move_group": 0,
		"ai_target_move_x": -1,
		"ai_target_move_y": -1,
		"ai_skill_function": "",
		"ai_attack": "",
		"ai_move": "",
		"ai_heal": "",
		"ai_skill": "",
		"ai_use": "",
		"skill_group_id": 0,
		"gear_GearGear": 41002,
		"gear_rank": 1,
		"proficiency_UnitProficiency": 1,
		"level": 46,
		"hp": 51,
		"strength": 44,
		"vitality": 41,
		"intelligence": 34,
		"mind": 30,
		"agility": 42,
		"dexterity": 39,
		"lucky": 12,
		"parameter_table_BattleEnemyParameterTable": 0,
		"parameter_deviation_table_BattleEnemyParameterDeviationTable": 0,
		"acquire_skill_group_id": 131,
		"level_correction": 0,
		"group_id": 0,
		"ai_script_id_BattleAIScript": 0
	},
	{
		"ID": 41746,
		"stage_BattleStage": 271002136,
		"unit_UnitUnit": 840004,
		"money": 230,
		"initial_coordinate_x": 8,
		"initial_coordinate_y": 1,
		"reinforcement_BattleReinforcement": 0,
		"initial_direction": 270.0,
		"ai_move_group": 0,
		"ai_target_move_x": -1,
		"ai_target_move_y": -1,
		"ai_skill_function": "",
		"ai_attack": "",
		"ai_move": "",
		"ai_heal": "",
		"ai_skill": "",
		"ai_use": "",
		"skill_group_id": 0,
		"gear_GearGear": 42001,
		"gear_rank": 1,
		"proficiency_UnitProficiency": 2,
		"level": 46,
		"hp": 57,
		"strength": 44,
		"vitality": 40,
		"intelligence": 31,
		"mind": 33,
		"agility": 39,
		"dexterity": 41,
		"lucky": 11,
		"parameter_table_BattleEnemyParameterTable": 0,
		"parameter_deviation_table_BattleEnemyParameterDeviationTable": 0,
		"acquire_skill_group_id": 131,
		"level_correction": 0,
		"group_id": 0,
		"ai_script_id_BattleAIScript": 0
	},
	{
		"ID": 41747,
		"stage_BattleStage": 271002136,
		"unit_UnitUnit": 820003,
		"money": 230,
		"initial_coordinate_x": 5,
		"initial_coordinate_y": 7,
		"reinforcement_BattleReinforcement": 0,
		"initial_direction": 270.0,
		"ai_move_group": 0,
		"ai_target_move_x": -1,
		"ai_target_move_y": -1,
		"ai_skill_function": "",
		"ai_attack": "",
		"ai_move": "",
		"ai_heal": "",
		"ai_skill": "",
		"ai_use": "",
		"skill_group_id": 0,
		"gear_GearGear": 21002,
		"gear_rank": 1,
		"proficiency_UnitProficiency": 1,
		"level": 46,
		"hp": 57,
		"strength": 47,
		"vitality": 46,
		"intelligence": 33,
		"mind": 27,
		"agility": 32,
		"dexterity": 35,
		"lucky": 10,
		"parameter_table_BattleEnemyParameterTable": 0,
		"parameter_deviation_table_BattleEnemyParameterDeviationTable": 0,
		"acquire_skill_group_id": 129,
		"level_correction": 0,
		"group_id": 0,
		"ai_script_id_BattleAIScript": 0
	},
	{
		"ID": 41748,
		"stage_BattleStage": 271002136,
		"unit_UnitUnit": 820003,
		"money": 230,
		"initial_coordinate_x": 5,
		"initial_coordinate_y": 6,
		"reinforcement_BattleReinforcement": 0,
		"initial_direction": 270.0,
		"ai_move_group": 0,
		"ai_target_move_x": -1,
		"ai_target_move_y": -1,
		"ai_skill_function": "",
		"ai_attack": "",
		"ai_move": "",
		"ai_heal": "",
		"ai_skill": "",
		"ai_use": "",
		"skill_group_id": 0,
		"gear_GearGear": 22001,
		"gear_rank": 1,
		"proficiency_UnitProficiency": 2,
		"level": 46,
		"hp": 60,
		"strength": 50,
		"vitality": 45,
		"intelligence": 31,
		"mind": 28,
		"agility": 34,
		"dexterity": 39,
		"lucky": 9,
		"parameter_table_BattleEnemyParameterTable": 0,
		"parameter_deviation_table_BattleEnemyParameterDeviationTable": 0,
		"acquire_skill_group_id": 129,
		"level_correction": 0,
		"group_id": 0,
		"ai_script_id_BattleAIScript": 0
	},
	{
		"ID": 41749,
		"stage_BattleStage": 271002136,
		"unit_UnitUnit": 820003,
		"money": 225,
		"initial_coordinate_x": 5,
		"initial_coordinate_y": 3,
		"reinforcement_BattleReinforcement": 0,
		"initial_direction": 270.0,
		"ai_move_group": 0,
		"ai_target_move_x": -1,
		"ai_target_move_y": -1,
		"ai_skill_function": "",
		"ai_attack": "",
		"ai_move": "",
		"ai_heal": "",
		"ai_skill": "",
		"ai_use": "",
		"skill_group_id": 0,
		"gear_GearGear": 21002,
		"gear_rank": 1,
		"proficiency_UnitProficiency": 1,
		"level": 45,
		"hp": 56,
		"strength": 45,
		"vitality": 44,
		"intelligence": 33,
		"mind": 29,
		"agility": 31,
		"dexterity": 34,
		"lucky": 8,
		"parameter_table_BattleEnemyParameterTable": 0,
		"parameter_deviation_table_BattleEnemyParameterDeviationTable": 0,
		"acquire_skill_group_id": 129,
		"level_correction": 0,
		"group_id": 0,
		"ai_script_id_BattleAIScript": 0
	},
	{
		"ID": 41750,
		"stage_BattleStage": 271002136,
		"unit_UnitUnit": 820003,
		"money": 230,
		"initial_coordinate_x": 5,
		"initial_coordinate_y": 2,
		"reinforcement_BattleReinforcement": 0,
		"initial_direction": 270.0,
		"ai_move_group": 0,
		"ai_target_move_x": -1,
		"ai_target_move_y": -1,
		"ai_skill_function": "",
		"ai_attack": "",
		"ai_move": "",
		"ai_heal": "",
		"ai_skill": "",
		"ai_use": "",
		"skill_group_id": 0,
		"gear_GearGear": 21002,
		"gear_rank": 1,
		"proficiency_UnitProficiency": 1,
		"level": 46,
		"hp": 62,
		"strength": 45,
		"vitality": 51,
		"intelligence": 30,
		"mind": 31,
		"agility": 34,
		"dexterity": 40,
		"lucky": 11,
		"parameter_table_BattleEnemyParameterTable": 0,
		"parameter_deviation_table_BattleEnemyParameterDeviationTable": 0,
		"acquire_skill_group_id": 129,
		"level_correction": 0,
		"group_id": 0,
		"ai_script_id_BattleAIScript": 0
	},
	{
		"ID": 41751,
		"stage_BattleStage": 271002136,
		"unit_UnitUnit": 900028,
		"money": 230,
		"initial_coordinate_x": 7,
		"initial_coordinate_y": 5,
		"reinforcement_BattleReinforcement": 0,
		"initial_direction": 270.0,
		"ai_move_group": 0,
		"ai_target_move_x": -1,
		"ai_target_move_y": -1,
		"ai_skill_function": "",
		"ai_attack": "",
		"ai_move": "IF(turn <=6,0,1)",
		"ai_heal": "",
		"ai_skill": "",
		"ai_use": "",
		"skill_group_id": 0,
		"gear_GearGear": 12003,
		"gear_rank": 1,
		"proficiency_UnitProficiency": 2,
		"level": 46,
		"hp": 51,
		"strength": 44,
		"vitality": 41,
		"intelligence": 28,
		"mind": 31,
		"agility": 39,
		"dexterity": 39,
		"lucky": 13,
		"parameter_table_BattleEnemyParameterTable": 0,
		"parameter_deviation_table_BattleEnemyParameterDeviationTable": 0,
		"acquire_skill_group_id": 61,
		"level_correction": 0,
		"group_id": 0,
		"ai_script_id_BattleAIScript": 0
	},
	{
		"ID": 41752,
		"stage_BattleStage": 271002136,
		"unit_UnitUnit": 900029,
		"money": 230,
		"initial_coordinate_x": 7,
		"initial_coordinate_y": 4,
		"reinforcement_BattleReinforcement": 0,
		"initial_direction": 270.0,
		"ai_move_group": 0,
		"ai_target_move_x": -1,
		"ai_target_move_y": -1,
		"ai_skill_function": "",
		"ai_attack": "",
		"ai_move": "IF(turn <=3,0,1)",
		"ai_heal": "",
		"ai_skill": "",
		"ai_use": "",
		"skill_group_id": 0,
		"gear_GearGear": 33003,
		"gear_rank": 1,
		"proficiency_UnitProficiency": 3,
		"level": 46,
		"hp": 57,
		"strength": 45,
		"vitality": 42,
		"intelligence": 32,
		"mind": 34,
		"agility": 40,
		"dexterity": 45,
		"lucky": 12,
		"parameter_table_BattleEnemyParameterTable": 0,
		"parameter_deviation_table_BattleEnemyParameterDeviationTable": 0,
		"acquire_skill_group_id": 46,
		"level_correction": 0,
		"group_id": 0,
		"ai_script_id_BattleAIScript": 0
	}
]