[
	{
		"ID": 1,
		"name": "マサムネストーリー",
		"quest_QuestCharacterS": 310011302,
		"priority": 1
	},
	{
		"ID": 2,
		"name": "レーヴァテインストーリー",
		"quest_QuestCharacterS": 310022302,
		"priority": 2
	},
	{
		"ID": 3,
		"name": "パラシュストーリー",
		"quest_QuestCharacterS": 320041302,
		"priority": 3
	},
	{
		"ID": 4,
		"name": "ロンギヌスストーリー",
		"quest_QuestCharacterS": 330011302,
		"priority": 4
	},
	{
		"ID": 5,
		"name": "アルテミスストーリー",
		"quest_QuestCharacterS": 340013302,
		"priority": 5
	},
	{
		"ID": 6,
		"name": "フライクーゲルストーリー",
		"quest_QuestCharacterS": 350021302,
		"priority": 6
	},
	{
		"ID": 7,
		"name": "デュランダルストーリー",
		"quest_QuestCharacterS": 310034202,
		"priority": 7
	},
	{
		"ID": 8,
		"name": "ミョルニルストーリー",
		"quest_QuestCharacterS": 320011202,
		"priority": 8
	},
	{
		"ID": 9,
		"name": "ミトゥムストーリー",
		"quest_QuestCharacterS": 320053202,
		"priority": 9
	},
	{
		"ID": 10,
		"name": "ルーンストーリー",
		"quest_QuestCharacterS": 330053202,
		"priority": 10
	},
	{
		"ID": 11,
		"name": "アポロンストーリー",
		"quest_QuestCharacterS": 340033202,
		"priority": 11
	},
	{
		"ID": 12,
		"name": "ブラフマーストラストーリー",
		"quest_QuestCharacterS": 350042202,
		"priority": 12
	},
	{
		"ID": 13,
		"name": "アスクレピオスストーリー",
		"quest_QuestCharacterS": 360013202,
		"priority": 13
	},
	{
		"ID": 14,
		"name": "ラブリュスストーリー",
		"quest_QuestCharacterS": 320034302,
		"priority": 14
	},
	{
		"ID": 15,
		"name": "シャルウルストーリー",
		"quest_QuestCharacterS": 320073202,
		"priority": 15
	},
	{
		"ID": 16,
		"name": "ロンギヌスストーリー",
		"quest_QuestCharacterS": 330013202,
		"priority": 16
	},
	{
		"ID": 17,
		"name": "レーヴァテインストーリー",
		"quest_QuestCharacterS": 310025302,
		"priority": 17
	},
	{
		"ID": 18,
		"name": "フライクーゲルストーリー",
		"quest_QuestCharacterS": 350023202,
		"priority": 18
	},
	{
		"ID": 19,
		"name": "エロースストーリー",
		"quest_QuestCharacterS": 340042202,
		"priority": 19
	},
	{
		"ID": 20,
		"name": "マサムネストーリー",
		"quest_QuestCharacterS": 310013202,
		"priority": 20
	},
	{
		"ID": 21,
		"name": "アロンダイトストーリー",
		"quest_QuestCharacterS": 310073202,
		"priority": 21
	},
	{
		"ID": 22,
		"name": "芭蕉扇ストーリー",
		"quest_QuestCharacterS": 350081202,
		"priority": 22
	},
	{
		"ID": 23,
		"name": "ゲイボルグストーリー",
		"quest_QuestCharacterS": 330071202,
		"priority": 23
	},
	{
		"ID": 24,
		"name": "グラムストーリー",
		"quest_QuestCharacterS": 310082202,
		"priority": 24
	},
	{
		"ID": 25,
		"name": "ペルーンストーリー",
		"quest_QuestCharacterS": 320084302,
		"priority": 25
	},
	{
		"ID": 26,
		"name": "アスクレピオスストーリー",
		"quest_QuestCharacterS": 360014302,
		"priority": 26
	},
	{
		"ID": 27,
		"name": "シェキナーストーリー",
		"quest_QuestCharacterS": 340071202,
		"priority": 27
	},
	{
		"ID": 28,
		"name": "ダグダストーリー",
		"quest_QuestCharacterS": 320064202,
		"priority": 28
	},
	{
		"ID": 29,
		"name": "ブリューナクストーリー",
		"quest_QuestCharacterS": 350072202,
		"priority": 29
	},
	{
		"ID": 30,
		"name": "ロンゴミアントストーリー",
		"quest_QuestCharacterS": 330103302,
		"priority": 30
	},
	{
		"ID": 31,
		"name": "みりんストーリー",
		"quest_QuestCharacterS": 310151302,
		"priority": 31
	},
	{
		"ID": 32,
		"name": "セレナストーリー",
		"quest_QuestCharacterS": 310171302,
		"priority": 32
	},
	{
		"ID": 33,
		"name": "ルナリスストーリー",
		"quest_QuestCharacterS": 330121302,
		"priority": 33
	},
	{
		"ID": 34,
		"name": "カドケウスストーリー",
		"quest_QuestCharacterS": 360043202,
		"priority": 34
	},
	{
		"ID": 35,
		"name": "えいたそストーリー",
		"quest_QuestCharacterS": 340091302,
		"priority": 35
	},
	{
		"ID": 36,
		"name": "ねむストーリー",
		"quest_QuestCharacterS": 320091302,
		"priority": 36
	},
	{
		"ID": 37,
		"name": "もがストーリー",
		"quest_QuestCharacterS": 350091302,
		"priority": 37
	},
	{
		"ID": 38,
		"name": "ピンキーストーリー",
		"quest_QuestCharacterS": 330111302,
		"priority": 38
	},
	{
		"ID": 39,
		"name": "リサストーリー",
		"quest_QuestCharacterS": 360071302,
		"priority": 39
	},
	{
		"ID": 40,
		"name": "でんぱストーリー",
		"quest_QuestCharacterS": 310181302,
		"priority": 40
	},
	{
		"ID": 41,
		"name": "グングニルストーリー",
		"quest_QuestCharacterS": 330083202,
		"priority": 41
	},
	{
		"ID": 42,
		"name": "エクスカリバーストーリー",
		"quest_QuestCharacterS": 310111202,
		"priority": 42
	},
	{
		"ID": 43,
		"name": "アルテミスストーリー",
		"quest_QuestCharacterS": 340012202,
		"priority": 43
	},
	{
		"ID": 44,
		"name": "草薙剣ストーリー",
		"quest_QuestCharacterS": 310042302,
		"priority": 44
	},
	{
		"ID": 45,
		"name": "天沼矛ストーリー",
		"quest_QuestCharacterS": 330043302,
		"priority": 45
	},
	{
		"ID": 46,
		"name": "アイムールストーリー",
		"quest_QuestCharacterS": 320022302,
		"priority": 46
	},
	{
		"ID": 47,
		"name": "イルダーナストーリー",
		"quest_QuestCharacterS": 330131302,
		"priority": 47
	},
	{
		"ID": 48,
		"name": "カノンストーリー",
		"quest_QuestCharacterS": 310191302,
		"priority": 48
	},
	{
		"ID": 49,
		"name": "ケラウノスストーリー",
		"quest_QuestCharacterS": 350013202,
		"priority": 49
	},
	{
		"ID": 50,
		"name": "エロースストーリー",
		"quest_QuestCharacterS": 340044202,
		"priority": 50
	},
	{
		"ID": 51,
		"name": "バルムンクストーリー",
		"quest_QuestCharacterS": 310091202,
		"priority": 51
	},
	{
		"ID": 52,
		"name": "ナーゲルリングストーリー",
		"quest_QuestCharacterS": 310062302,
		"priority": 52
	},
	{
		"ID": 53,
		"name": "トライデントストーリー",
		"quest_QuestCharacterS": 330023302,
		"priority": 53
	},
	{
		"ID": 54,
		"name": "ミストルティンストーリー",
		"quest_QuestCharacterS": 360062302,
		"priority": 54
	},
	{
		"ID": 55,
		"name": "八咫鏡ストーリー",
		"quest_QuestCharacterS": 350033302,
		"priority": 55
	},
	{
		"ID": 56,
		"name": "ケーリュケイオンストーリー",
		"quest_QuestCharacterS": 360053202,
		"priority": 56
	},
	{
		"ID": 57,
		"name": "イシューリエルストーリー",
		"quest_QuestCharacterS": 330142202,
		"priority": 57
	},
	{
		"ID": 58,
		"name": "マサムネストーリー",
		"quest_QuestCharacterS": 310015302,
		"priority": 58
	},
	{
		"ID": 59,
		"name": "オティヌスストーリー",
		"quest_QuestCharacterS": 340082302,
		"priority": 59
	},
	{
		"ID": 60,
		"name": "パラシュストーリー",
		"quest_QuestCharacterS": 320045302,
		"priority": 60
	},
	{
		"ID": 61,
		"name": "パラケルススストーリー",
		"quest_QuestCharacterS": 310131202,
		"priority": 61
	},
	{
		"ID": 62,
		"name": "トリシューラストーリー",
		"quest_QuestCharacterS": 330063302,
		"priority": 62
	},
	{
		"ID": 64,
		"name": "梓弓ストーリー",
		"quest_QuestCharacterS": 340062302,
		"priority": 64
	},
	{
		"ID": 65,
		"name": "テュルソスストーリー",
		"quest_QuestCharacterS": 360032302,
		"priority": 65
	},
	{
		"ID": 66,
		"name": "アロンダイトストーリー",
		"quest_QuestCharacterS": 310071302,
		"priority": 66
	},
	{
		"ID": 67,
		"name": "ウコンバサラストーリー",
		"quest_QuestCharacterS": 320101202,
		"priority": 67
	},
	{
		"ID": 68,
		"name": "ロンギヌスストーリー",
		"quest_QuestCharacterS": 330015302,
		"priority": 68
	},
	{
		"ID": 69,
		"name": "リットゥストーリー",
		"quest_QuestCharacterS": 310053302,
		"priority": 69
	},
	{
		"ID": 70,
		"name": "常守朱ストーリー",
		"quest_QuestCharacterS": 350101302,
		"priority": 70
	},
	{
		"ID": 71,
		"name": "六合塚弥生ストーリー",
		"quest_QuestCharacterS": 350111302,
		"priority": 71
	},
	{
		"ID": 72,
		"name": "霜月美佳ストーリー",
		"quest_QuestCharacterS": 350121302,
		"priority": 72
	},
	{
		"ID": 73,
		"name": "レーヴァテインストーリー",
		"quest_QuestCharacterS": 310026302,
		"priority": 73
	},
	{
		"ID": 74,
		"name": "スラーンドストーリー",
		"quest_QuestCharacterS": 320122202,
		"priority": 74
	},
	{
		"ID": 75,
		"name": "アルテミスストーリー",
		"quest_QuestCharacterS": 340014302,
		"priority": 75
	},
	{
		"ID": 76,
		"name": "グリダヴォルストーリー",
		"quest_QuestCharacterS": 360081202,
		"priority": 76
	},
	{
		"ID": 77,
		"name": "シェキナーストーリー",
		"quest_QuestCharacterS": 340074302,
		"priority": 77
	},
	{
		"ID": 78,
		"name": "パラシュストーリー",
		"quest_QuestCharacterS": 320043202,
		"priority": 78
	},
	{
		"ID": 79,
		"name": "鹿目まどかストーリー",
		"quest_QuestCharacterS": 340111302,
		"priority": 79
	},
	{
		"ID": 80,
		"name": "暁美ほむらストーリー",
		"quest_QuestCharacterS": 350131302,
		"priority": 80
	},
	{
		"ID": 81,
		"name": "美樹さやかストーリー",
		"quest_QuestCharacterS": 310201302,
		"priority": 81
	},
	{
		"ID": 82,
		"name": "佐倉杏子ストーリー",
		"quest_QuestCharacterS": 330151302,
		"priority": 82
	},
	{
		"ID": 83,
		"name": "巴マミストーリー",
		"quest_QuestCharacterS": 350141302,
		"priority": 83
	},
	{
		"ID": 84,
		"name": "アルティメットまどかストーリー",
		"quest_QuestCharacterS": 340112302,
		"priority": 84
	},
	{
		"ID": 85,
		"name": "青龍偃月刀ストーリー",
		"quest_QuestCharacterS": 330091202,
		"priority": 85
	},
	{
		"ID": 86,
		"name": "バルムンクストーリー",
		"quest_QuestCharacterS": 310092202,
		"priority": 86
	},
	{
		"ID": 87,
		"name": "めんまストーリー",
		"quest_QuestCharacterS": 310211302,
		"priority": 87
	},
	{
		"ID": 88,
		"name": "あなるストーリー",
		"quest_QuestCharacterS": 320141302,
		"priority": 88
	},
	{
		"ID": 89,
		"name": "つるこストーリー",
		"quest_QuestCharacterS": 330161302,
		"priority": 89
	},
	{
		"ID": 90,
		"name": "芭蕉扇（ハロウィンver）ストーリー",
		"quest_QuestCharacterS": 350084302,
		"priority": 90
	},
	{
		"ID": 91,
		"name": "ロンゴミアント2ストーリー",
		"quest_QuestCharacterS": 330102202,
		"priority": 91
	},
	{
		"ID": 92,
		"name": "レシェフストーリー",
		"quest_QuestCharacterS": 320131202,
		"priority": 92
	},
	{
		"ID": 93,
		"name": "ガンバンテイン(ハロウィンver)ストーリー",
		"quest_QuestCharacterS": 360023302,
		"priority": 93
	},
	{
		"ID": 94,
		"name": "ハロウィンミョルニルストーリー",
		"quest_QuestCharacterS": 320015302,
		"priority": 94
	},
	{
		"ID": 95,
		"name": "ティルフィングストーリー",
		"quest_QuestCharacterS": 310141401,
		"priority": 999
	},
	{
		"ID": 96,
		"name": "ルキナストーリー",
		"quest_QuestCharacterS": 310221302,
		"priority": 96
	},
	{
		"ID": 97,
		"name": "ミセルストーリー",
		"quest_QuestCharacterS": 320151302,
		"priority": 97
	},
	{
		"ID": 98,
		"name": "シタストーリー",
		"quest_QuestCharacterS": 320162301,
		"priority": 98
	},
	{
		"ID": 99,
		"name": "メギドストーリー",
		"quest_QuestCharacterS": 350061202,
		"priority": 99
	},
	{
		"ID": 100,
		"name": "フラベルムストーリー",
		"quest_QuestCharacterS": 350161301,
		"priority": 100
	},
	{
		"ID": 101,
		"name": "グリモワールストーリー",
		"quest_QuestCharacterS": 350171301,
		"priority": 101
	},
	{
		"ID": 102,
		"name": "ヤグルシストーリー",
		"quest_QuestCharacterS": 320171301,
		"priority": 102
	},
	{
		"ID": 103,
		"name": "与一ストーリー",
		"quest_QuestCharacterS": 340055301,
		"priority": 103
	},
	{
		"ID": 104,
		"name": "アイムール(クリスマスver)ストーリー",
		"quest_QuestCharacterS": 320025301,
		"priority": 104
	},
	{
		"ID": 105,
		"name": "グラム（クリスマスver）ストーリー",
		"quest_QuestCharacterS": 310084301,
		"priority": 105
	},
	{
		"ID": 106,
		"name": "フランキスカストーリー",
		"quest_QuestCharacterS": 320181301,
		"priority": 106
	},
	{
		"ID": 107,
		"name": "悪魔ほむらストーリー",
		"quest_QuestCharacterS": 350181301,
		"priority": 107
	},
	{
		"ID": 110,
		"name": "アスカロンストーリー",
		"quest_QuestCharacterS": 310231301,
		"priority": 110
	},
	{
		"ID": 111,
		"name": "レーヴァテイン4ストーリー",
		"quest_QuestCharacterS": 310024301,
		"priority": 111
	},
	{
		"ID": 112,
		"name": "ピナーカストーリー",
		"quest_QuestCharacterS": 340023302,
		"priority": 112
	},
	{
		"ID": 113,
		"name": "ヴァジュラストーリー",
		"quest_QuestCharacterS": 350053302,
		"priority": 113
	},
	{
		"ID": 114,
		"name": "タスラム",
		"quest_QuestCharacterS": 350201301,
		"priority": 114
	},
	{
		"ID": 115,
		"name": "VTティルフォング",
		"quest_QuestCharacterS": 310145301,
		"priority": 115
	},
	{
		"ID": 116,
		"name": "フォルカス",
		"quest_QuestCharacterS": 330181301,
		"priority": 116
	},
	{
		"ID": 117,
		"name": "アフロディーテ",
		"quest_QuestCharacterS": 340131301,
		"priority": 117
	},
	{
		"ID": 118,
		"name": "アダマス",
		"quest_QuestCharacterS": 310122302,
		"priority": 118
	},
	{
		"ID": 113,
		"name": "ワズラストーリー",
		"quest_QuestCharacterS": 320111301,
		"priority": 119
	},
	{
		"ID": 118,
		"name": "オティヌスストーリー2",
		"quest_QuestCharacterS": 340083301,
		"priority": 120
	},
	{
		"ID": 121,
		"name": "セイバーストーリー1（☆6）",
		"quest_QuestCharacterS": 310242302,
		"priority": 121
	},
	{
		"ID": 122,
		"name": "セイバーストーリー2（☆5）",
		"quest_QuestCharacterS": 310241202,
		"priority": 122
	},
	{
		"ID": 123,
		"name": "凛ストーリー",
		"quest_QuestCharacterS": 350191301,
		"priority": 123
	},
	{
		"ID": 124,
		"name": "イリヤストーリー",
		"quest_QuestCharacterS": 360101301,
		"priority": 124
	},
	{
		"ID": 125,
		"name": "ライダーストーリー",
		"quest_QuestCharacterS": 330191301,
		"priority": 125
	},
	{
		"ID": 126,
		"name": "ムラマサストーリー",
		"quest_QuestCharacterS": 310251301,
		"priority": 126
	},
	{
		"ID": 127,
		"name": "シユウストーリー",
		"quest_QuestCharacterS": 320191301,
		"priority": 127
	},
	{
		"ID": 128,
		"name": "ヴォータンストーリー",
		"quest_QuestCharacterS": 330171301,
		"priority": 128
	},
	{
		"ID": 129,
		"name": "方天画戟ストーリー",
		"quest_QuestCharacterS": 330033301,
		"priority": 129
	},
	{
		"ID": 130,
		"name": "ヴァナルガンドストーリー",
		"quest_QuestCharacterS": 360111301,
		"priority": 130
	},
	{
		"ID": 131,
		"name": "フラガラッハストーリー",
		"quest_QuestCharacterS": 310102302,
		"priority": 131
	},
	{
		"ID": 132,
		"name": "カラドボルグストーリー",
		"quest_QuestCharacterS": 310261301,
		"priority": 132
	},
	{
		"ID": 133,
		"name": "クラウ・ソラスストーリー",
		"quest_QuestCharacterS": 310271301,
		"priority": 133
	},
	{
		"ID": 134,
		"name": "制服グリモワールストーリー",
		"quest_QuestCharacterS": 350172301,
		"priority": 134
	},
	{
		"ID": 135,
		"name": "制服トリシューラストーリー",
		"quest_QuestCharacterS": 330064301,
		"priority": 135
	},
	{
		"ID": 136,
		"name": "ウロボロスストーリー",
		"quest_QuestCharacterS": 360121301,
		"priority": 136
	},
	{
		"ID": 137,
		"name": "シストルムストーリー",
		"quest_QuestCharacterS": 360131301,
		"priority": 137
	},
	{
		"ID": 138,
		"name": "ピサールストーリー",
		"quest_QuestCharacterS": 330201301,
		"priority": 138
	},
	{
		"ID": 139,
		"name": "アロンダイトストーリー",
		"quest_QuestCharacterS": 310072301,
		"priority": 139
	},
	{
		"ID": 140,
		"name": "ガ・ボーストーリー",
		"quest_QuestCharacterS": 330211301,
		"priority": 140
	},
	{
		"ID": 141,
		"name": "プタハストーリー",
		"quest_QuestCharacterS": 360141301,
		"priority": 141
	},
	{
		"ID": 142,
		"name": "フライクーゲルストーリー",
		"quest_QuestCharacterS": 350024301,
		"priority": 142
	},
	{
		"ID": 143,
		"name": "ハルパーストーリー",
		"quest_QuestCharacterS": 320201301,
		"priority": 143
	},
	{
		"ID": 146,
		"name": "梓弓",
		"quest_QuestCharacterS": 340061301,
		"priority": 146
	},
	{
		"ID": 147,
		"name": "草薙剣",
		"quest_QuestCharacterS": 310044301,
		"priority": 147
	},
	{
		"ID": 148,
		"name": "ダーインスレイヴ",
		"quest_QuestCharacterS": 310281301,
		"priority": 148
	},
	{
		"ID": 149,
		"name": "天沼矛",
		"quest_QuestCharacterS": 330044301,
		"priority": 149
	},
	{
		"ID": 145,
		"name": "ミョルニル2ストーリー",
		"quest_QuestCharacterS": 320012301,
		"priority": 150
	},
	{
		"ID": 150,
		"name": "アスカロン",
		"quest_QuestCharacterS": 310235301,
		"priority": 151
	},
	{
		"ID": 151,
		"name": "ウエディング芭蕉扇",
		"quest_QuestCharacterS": 350085201,
		"priority": 152
	},
	{
		"ID": 144,
		"name": "セファー",
		"quest_QuestCharacterS": 350211301,
		"priority": 153
	},
	{
		"ID": 152,
		"name": "グリダヴォル",
		"quest_QuestCharacterS": 360085301,
		"priority": 154
	},
	{
		"ID": 153,
		"name": "ヤグルシ",
		"quest_QuestCharacterS": 320175301,
		"priority": 155
	},
	{
		"ID": 154,
		"name": "パラシュ",
		"quest_QuestCharacterS": 320046301,
		"priority": 156
	},
	{
		"ID": 155,
		"name": "パラケルスス2ストーリー",
		"quest_QuestCharacterS": 310133301,
		"priority": 157
	},
	{
		"ID": 156,
		"name": "エロース水着ストーリー",
		"quest_QuestCharacterS": 340045301,
		"priority": 158
	},
	{
		"ID": 155,
		"name": "浴衣フォルカスストーリー",
		"quest_QuestCharacterS": 330185301,
		"priority": 156
	},
	{
		"ID": 156,
		"name": "制服アロンダイトストーリー",
		"quest_QuestCharacterS": 310075301,
		"priority": 157
	},
	{
		"ID": 157,
		"name": "ティルフィング",
		"quest_QuestCharacterS": 310146301,
		"priority": 158
	},
	{
		"ID": 158,
		"name": "フライクーゲル",
		"quest_QuestCharacterS": 350025301,
		"priority": 159
	},
	{
		"ID": 159,
		"name": "ヨミ",
		"quest_QuestCharacterS": 310311301,
		"priority": 160
	},
	{
		"ID": 160,
		"name": "アルミラ",
		"quest_QuestCharacterS": 340161301,
		"priority": 161
	},
	{
		"ID": 161,
		"name": "画集用エクスカリバー",
		"quest_QuestCharacterS": 310115301,
		"priority": 162
	},
	{
		"ID": 162,
		"name": "ロンギヌスストーリー",
		"quest_QuestCharacterS": 330016301,
		"priority": 163
	},
	{
		"ID": 163,
		"name": "フラガラッハストーリー",
		"quest_QuestCharacterS": 310101301,
		"priority": 164
	},
	{
		"ID": 164,
		"name": "デュランダルストーリー",
		"quest_QuestCharacterS": 310035301,
		"priority": 165
	},
	{
		"ID": 165,
		"name": "体操服レーヴァテインストーリー",
		"quest_QuestCharacterS": 310027301,
		"priority": 166
	},
	{
		"ID": 166,
		"name": "制服ラブリュスストーリー",
		"quest_QuestCharacterS": 320035301,
		"priority": 167
	},
	{
		"ID": 167,
		"name": "制服ケラウノスストーリー",
		"quest_QuestCharacterS": 350015301,
		"priority": 168
	},
	{
		"ID": 168,
		"name": "体操服ケラウノスストーリー",
		"quest_QuestCharacterS": 350014301,
		"priority": 169
	},
	{
		"ID": 169,
		"name": "バルムンクストーリー",
		"quest_QuestCharacterS": 310094301,
		"priority": 170
	},
	{
		"ID": 170,
		"name": "マサムネ_黒_ストーリー",
		"quest_QuestCharacterS": 310016301,
		"priority": 171
	},
	{
		"ID": 171,
		"name": "アルテミス_黒_ストーリー",
		"quest_QuestCharacterS": 340015301,
		"priority": 172
	},
	{
		"ID": 172,
		"name": "シユウ_ハロウィン_ストーリー",
		"quest_QuestCharacterS": 320195301,
		"priority": 173
	},
	{
		"ID": 173,
		"name": "イシューリエル_ハロウィン_ストーリー",
		"quest_QuestCharacterS": 330141301,
		"priority": 174
	},
	{
		"ID": 174,
		"name": "ティルフィング_黒_ストーリー",
		"quest_QuestCharacterS": 310147301,
		"priority": 175
	},
	{
		"ID": 175,
		"name": "シェキナー_メイドストーリー",
		"quest_QuestCharacterS": 340076301,
		"priority": 176
	},
	{
		"ID": 176,
		"name": "ナーゲルリング_メイドストーリー",
		"quest_QuestCharacterS": 310065301,
		"priority": 177
	},
	{
		"ID": 177,
		"name": "ダグダ_教師ストーリー",
		"quest_QuestCharacterS": 320065301,
		"priority": 178
	},
	{
		"ID": 178,
		"name": "シェキナー_制服ストーリー",
		"quest_QuestCharacterS": 340075301,
		"priority": 179
	},
	{
		"ID": 179,
		"name": "シェイナ",
		"quest_QuestCharacterS": 320231301,
		"priority": 180
	},
	{
		"ID": 180,
		"name": "ローザ",
		"quest_QuestCharacterS": 320241301,
		"priority": 181
	},
	{
		"ID": 181,
		"name": "フライクーゲル_黒_ストーリー",
		"quest_QuestCharacterS": 350026301,
		"priority": 182
	},
	{
		"ID": 182,
		"name": "レーヴァテイン_黒_ストーリー",
		"quest_QuestCharacterS": 310028301,
		"priority": 183
	},
	{
		"ID": 183,
		"name": "芭蕉扇_制服ストーリー",
		"quest_QuestCharacterS": 350086301,
		"priority": 184
	},
	{
		"ID": 184,
		"name": "与一_制服ストーリー",
		"quest_QuestCharacterS": 340056301,
		"priority": 185
	},
	{
		"ID": 185,
		"name": "リサストーリー",
		"quest_QuestCharacterS": 310301303,
		"priority": 186
	},
	{
		"ID": 186,
		"name": "ピンキーストーリー",
		"quest_QuestCharacterS": 320211303,
		"priority": 187
	},
	{
		"ID": 187,
		"name": "もがストーリー",
		"quest_QuestCharacterS": 330221303,
		"priority": 188
	},
	{
		"ID": 188,
		"name": "ねむストーリー",
		"quest_QuestCharacterS": 340141303,
		"priority": 189
	},
	{
		"ID": 189,
		"name": "みりんストーリー",
		"quest_QuestCharacterS": 350221303,
		"priority": 190
	},
	{
		"ID": 190,
		"name": "えいたそストーリー",
		"quest_QuestCharacterS": 360151303,
		"priority": 191
	},
	{
		"ID": 191,
		"name": "蜻蛉切ストーリー",
		"quest_QuestCharacterS": 330241301,
		"priority": 192
	},
	{
		"ID": 192,
		"name": "クリスマス_アフロディーテ_ストーリー",
		"quest_QuestCharacterS": 340133301,
		"priority": 193
	},
	{
		"ID": 193,
		"name": "クリスマス_ロンギヌス_ストーリー",
		"quest_QuestCharacterS": 330017301,
		"priority": 194
	},
	{
		"ID": 194,
		"name": "ケーリュケイオン_ストーリー",
		"quest_QuestCharacterS": 360052301,
		"priority": 195
	},
	{
		"ID": 195,
		"name": "クリスマス_ブリューナク",
		"quest_QuestCharacterS": 350073301,
		"priority": 196
	},
	{
		"ID": 196,
		"name": "蘇生アスクレピオス",
		"quest_QuestCharacterS": 360015301,
		"priority": 197
	},
	{
		"ID": 197,
		"name": "学園_シタ",
		"quest_QuestCharacterS": 320164301,
		"priority": 198
	},
	{
		"ID": 198,
		"name": "学園_ミトゥム",
		"quest_QuestCharacterS": 320054301,
		"priority": 199
	},
	{
		"ID": 199,
		"name": "学園_ミストルティン",
		"quest_QuestCharacterS": 360063301,
		"priority": 200
	},
	{
		"ID": 200,
		"name": "人気投票1位フォルカス",
		"quest_QuestCharacterS": 330183301,
		"priority": 201
	},
	{
		"ID": 201,
		"name": "正月_アロンダイト",
		"quest_QuestCharacterS": 310074301,
		"priority": 202
	},
	{
		"ID": 202,
		"name": "正月_ヴァナルガンド",
		"quest_QuestCharacterS": 360113301,
		"priority": 203
	},
	{
		"ID": 203,
		"name": "正月_梓弓",
		"quest_QuestCharacterS": 340063301,
		"priority": 204
	},
	{
		"ID": 204,
		"name": "新ジョブ_アバリス",
		"quest_QuestCharacterS": 340102301,
		"priority": 205
	},
	{
		"ID": 205,
		"name": "新ゲイボルグ",
		"quest_QuestCharacterS": 330074301,
		"priority": 206
	},
	{
		"ID": 206,
		"name": "雑賀",
		"quest_QuestCharacterS": 350241301,
		"priority": 207
	},
	{
		"ID": 207,
		"name": "キキョウ",
		"quest_QuestCharacterS": 330231301,
		"priority": 208
	},
	{
		"ID": 208,
		"name": "サクラ",
		"quest_QuestCharacterS": 310321301,
		"priority": 209
	},
	{
		"ID": 209,
		"name": "ヒイラギ",
		"quest_QuestCharacterS": 350231301,
		"priority": 210
	},
	{
		"ID": 210,
		"name": "ユリ",
		"quest_QuestCharacterS": 340151301,
		"priority": 211
	},
	{
		"ID": 211,
		"name": "クロエ",
		"quest_QuestCharacterS": 310331301,
		"priority": 212
	},
	{
		"ID": 212,
		"name": "レナ",
		"quest_QuestCharacterS": 360161301,
		"priority": 213
	},
	{
		"ID": 213,
		"name": "黒パラシュ",
		"quest_QuestCharacterS": 320047301,
		"priority": 214
	},
	{
		"ID": 214,
		"name": "黒ロンギヌス",
		"quest_QuestCharacterS": 330018301,
		"priority": 215
	},
	{
		"ID": 215,
		"name": "学園ピサール",
		"quest_QuestCharacterS": 330202301,
		"priority": 216
	},
	{
		"ID": 216,
		"name": "学園ムラマサ",
		"quest_QuestCharacterS": 310253301,
		"priority": 217
	},
	{
		"ID": 217,
		"name": "学園八咫鏡",
		"quest_QuestCharacterS": 350034301,
		"priority": 218
	},
	{
		"ID": 218,
		"name": "アクア（羽衣）",
		"quest_QuestCharacterS": 360172301,
		"priority": 219
	},
	{
		"ID": 219,
		"name": "アクア",
		"quest_QuestCharacterS": 360171301,
		"priority": 220
	},
	{
		"ID": 220,
		"name": "このすば_グリモワール",
		"quest_QuestCharacterS": 350174301,
		"priority": 221
	},
	{
		"ID": 221,
		"name": "このすば_ヤグルシ",
		"quest_QuestCharacterS": 320173301,
		"priority": 222
	},
	{
		"ID": 222,
		"name": "ダクネス(鎧)",
		"quest_QuestCharacterS": 310341301,
		"priority": 223
	},
	{
		"ID": 223,
		"name": "ダクネス（鎧なし）",
		"quest_QuestCharacterS": 310342301,
		"priority": 224
	},
	{
		"ID": 224,
		"name": "めぐみん（眼帯あり）",
		"quest_QuestCharacterS": 350252301,
		"priority": 225
	},
	{
		"ID": 225,
		"name": "めぐみん（眼帯なし）",
		"quest_QuestCharacterS": 350251301,
		"priority": 226
	},
	{
		"ID": 226,
		"name": "ゆんゆん",
		"quest_QuestCharacterS": 350261301,
		"priority": 227
	},
	{
		"ID": 227,
		"name": "ウィズ",
		"quest_QuestCharacterS": 360181301,
		"priority": 228
	},
	{
		"ID": 228,
		"name": "3月学園マサムネ",
		"quest_QuestCharacterS": 310017301,
		"priority": 229
	},
	{
		"ID": 229,
		"name": "3月学園ダーインスレイヴ",
		"quest_QuestCharacterS": 310282301,
		"priority": 230
	},
	{
		"ID": 230,
		"name": "3月学園方天画戟",
		"quest_QuestCharacterS": 330035301,
		"priority": 231
	},
	{
		"ID": 231,
		"name": "ペルーン",
		"quest_QuestCharacterS": 320085301,
		"priority": 232
	},
	{
		"ID": 232,
		"name": "グングニル",
		"quest_QuestCharacterS": 330084301,
		"priority": 233
	},
	{
		"ID": 233,
		"name": "フライシュッツ",
		"quest_QuestCharacterS": 350271301,
		"priority": 234
	},
	{
		"ID": 234,
		"name": "ミネルヴァ",
		"quest_QuestCharacterS": 330251301,
		"priority": 235
	},
	{
		"ID": 235,
		"name": "ＭＡＩちゃん",
		"quest_QuestCharacterS": 360191301,
		"priority": 236
	},
	{
		"ID": 236,
		"name": "アスカロン",
		"quest_QuestCharacterS": 310232301,
		"priority": 237
	},
	{
		"ID": 237,
		"name": "アフロディーテ",
		"quest_QuestCharacterS": 340132301,
		"priority": 238
	},
	{
		"ID": 238,
		"name": "ヴァナルガンド",
		"quest_QuestCharacterS": 360112301,
		"priority": 239
	},
	{
		"ID": 239,
		"name": "グリモワール",
		"quest_QuestCharacterS": 350173301,
		"priority": 240
	},
	{
		"ID": 240,
		"name": "シユウ",
		"quest_QuestCharacterS": 320192301,
		"priority": 241
	},
	{
		"ID": 241,
		"name": "フォルカス",
		"quest_QuestCharacterS": 330182301,
		"priority": 242
	},
	{
		"ID": 242,
		"name": "ムラマサ",
		"quest_QuestCharacterS": 310252301,
		"priority": 243
	},
	{
		"ID": 243,
		"name": "4月学園オティヌス",
		"quest_QuestCharacterS": 340084301,
		"priority": 244
	},
	{
		"ID": 244,
		"name": "4月学園ブラフマーストラ",
		"quest_QuestCharacterS": 350043301,
		"priority": 245
	},
	{
		"ID": 245,
		"name": "4月学園グラム",
		"quest_QuestCharacterS": 310085301,
		"priority": 246
	},
	{
		"ID": 246,
		"name": "5月青龍偃月刀",
		"quest_QuestCharacterS": 330093301,
		"priority": 247
	},
	{
		"ID": 247,
		"name": "ラグナロク",
		"quest_QuestCharacterS": 310361301,
		"priority": 248
	},
	{
		"ID": 248,
		"name": "5月シェキナー",
		"quest_QuestCharacterS": 340072301,
		"priority": 249
	},
	{
		"ID": 249,
		"name": "スイハ",
		"quest_QuestCharacterS": 340171301,
		"priority": 250
	},
	{
		"ID": 250,
		"name": "ダモクレス",
		"quest_QuestCharacterS": 310351301,
		"priority": 251
	},
	{
		"ID": 251,
		"name": "5月学園パラシュ",
		"quest_QuestCharacterS": 320048301,
		"priority": 252
	},
	{
		"ID": 252,
		"name": "5月学園リットゥ",
		"quest_QuestCharacterS": 310054301,
		"priority": 253
	},
	{
		"ID": 253,
		"name": "5月学園タスラム",
		"quest_QuestCharacterS": 350202301,
		"priority": 254
	},
	{
		"ID": 254,
		"name": "エルキュール",
		"quest_QuestCharacterS": 320251301,
		"priority": 255
	},
	{
		"ID": 255,
		"name": "花嫁エロース",
		"quest_QuestCharacterS": 340046301,
		"priority": 256
	},
	{
		"ID": 256,
		"name": "花嫁ミストルティン",
		"quest_QuestCharacterS": 360064301,
		"priority": 257
	},
	{
		"ID": 257,
		"name": "グラーシーザ",
		"quest_QuestCharacterS": 330261301,
		"priority": 258
	},
	{
		"ID": 258,
		"name": "ネス",
		"quest_QuestCharacterS": 360201301,
		"priority": 259
	},
	{
		"ID": 259,
		"name": "ガブリエル",
		"quest_QuestCharacterS": 350281301,
		"priority": 260
	},
	{
		"ID": 260,
		"name": "ミウナ",
		"quest_QuestCharacterS": 320261301,
		"priority": 261
	},
	{
		"ID": 261,
		"name": "ヤウラス",
		"quest_QuestCharacterS": 310371301,
		"priority": 262
	},
	{
		"ID": 261,
		"name": "アスカロン",
		"quest_QuestCharacterS": 321023131,
		"priority": 263
	},
	{
		"ID": 262,
		"name": "芭蕉扇",
		"quest_QuestCharacterS": 325008131,
		"priority": 264
	},
	{
		"ID": 263,
		"name": "グングニル",
		"quest_QuestCharacterS": 323008131,
		"priority": 265
	},
	{
		"ID": 264,
		"name": "シタ",
		"quest_QuestCharacterS": 322016131,
		"priority": 266
	},
	{
		"ID": 265,
		"name": "ハルパー",
		"quest_QuestCharacterS": 322020131,
		"priority": 267
	},
	{
		"ID": 266,
		"name": "ペルーン",
		"quest_QuestCharacterS": 322008131,
		"priority": 268
	},
	{
		"ID": 267,
		"name": "天沼矛",
		"quest_QuestCharacterS": 323004131,
		"priority": 269
	},
	{
		"ID": 268,
		"name": "与一",
		"quest_QuestCharacterS": 324005131,
		"priority": 270
	},
	{
		"ID": 269,
		"name": "グラム",
		"quest_QuestCharacterS": 321008131,
		"priority": 271
	},
	{
		"ID": 270,
		"name": "蜻蛉切",
		"quest_QuestCharacterS": 323024131,
		"priority": 272
	},
	{
		"ID": 273,
		"name": "グリダヴォル",
		"quest_QuestCharacterS": 326008131,
		"priority": 273
	},
	{
		"ID": 274,
		"name": "バルムンク",
		"quest_QuestCharacterS": 321009131,
		"priority": 274
	},
	{
		"ID": 275,
		"name": "ピナーカ",
		"quest_QuestCharacterS": 324002131,
		"priority": 275
	},
	{
		"ID": 276,
		"name": "八咫鏡",
		"quest_QuestCharacterS": 325003131,
		"priority": 276
	},
	{
		"ID": 277,
		"name": "草薙剣",
		"quest_QuestCharacterS": 321004131,
		"priority": 277
	},
	{
		"ID": 278,
		"name": "アルテミス",
		"quest_QuestCharacterS": 324001131,
		"priority": 278
	},
	{
		"ID": 279,
		"name": "クラウ・ソラス",
		"quest_QuestCharacterS": 321027131,
		"priority": 279
	},
	{
		"ID": 280,
		"name": "ケラウノス",
		"quest_QuestCharacterS": 325001131,
		"priority": 280
	},
	{
		"ID": 281,
		"name": "メギド",
		"quest_QuestCharacterS": 325006131,
		"priority": 281
	},
	{
		"ID": 282,
		"name": "方天画戟",
		"quest_QuestCharacterS": 323003131,
		"priority": 282
	},
	{
		"ID": 283,
		"name": "アダマス",
		"quest_QuestCharacterS": 321012131,
		"priority": 283
	},
	{
		"ID": 284,
		"name": "エクスカリバー",
		"quest_QuestCharacterS": 321011131,
		"priority": 284
	},
	{
		"ID": 285,
		"name": "ミトゥム",
		"quest_QuestCharacterS": 322005131,
		"priority": 285
	},
	{
		"ID": 286,
		"name": "シストルム",
		"quest_QuestCharacterS": 326013131,
		"priority": 286
	},
	{
		"ID": 287,
		"name": "アバリス",
		"quest_QuestCharacterS": 324010131,
		"priority": 287
	},
	{
		"ID": 288,
		"name": "ユリ",
		"quest_QuestCharacterS": 340152301,
		"priority": 288
	},
	{
		"ID": 289,
		"name": "リズベット",
		"quest_QuestCharacterS": 360211301,
		"priority": 289
	},
	{
		"ID": 290,
		"name": "アマテラス",
		"quest_QuestCharacterS": 330271301,
		"priority": 290
	},
	{
		"ID": 291,
		"name": "ミョルニル",
		"quest_QuestCharacterS": 322001131,
		"priority": 291
	},
	{
		"ID": 292,
		"name": "ロンギヌス",
		"quest_QuestCharacterS": 323001131,
		"priority": 292
	},
	{
		"ID": 293,
		"name": "フォルカス",
		"quest_QuestCharacterS": 323018121,
		"priority": 293
	},
	{
		"ID": 294,
		"name": "シェキナー",
		"quest_QuestCharacterS": 324007121,
		"priority": 294
	},
	{
		"ID": 295,
		"name": "アスクレピオス",
		"quest_QuestCharacterS": 326001121,
		"priority": 295
	},
	{
		"ID": 296,
		"name": "ヤグルシ",
		"quest_QuestCharacterS": 322017121,
		"priority": 296
	},
	{
		"ID": 297,
		"name": "ガ・ボー",
		"quest_QuestCharacterS": 323021121,
		"priority": 297
	},
	{
		"ID": 298,
		"name": "ブリューナク",
		"quest_QuestCharacterS": 325007121,
		"priority": 298
	},
	{
		"ID": 299,
		"name": "トリシューラ",
		"quest_QuestCharacterS": 323006121,
		"priority": 299
	},
	{
		"ID": 300,
		"name": "ラブリュス",
		"quest_QuestCharacterS": 322003121,
		"priority": 300
	},
	{
		"ID": 301,
		"name": "パラシュ",
		"quest_QuestCharacterS": 322004121,
		"priority": 301
	},
	{
		"ID": 302,
		"name": "グリモワール",
		"quest_QuestCharacterS": 325017121,
		"priority": 302
	},
	{
		"ID": 303,
		"name": "リットゥ",
		"quest_QuestCharacterS": 321005121,
		"priority": 303
	},
	{
		"ID": 304,
		"name": "ダーインスレイブ",
		"quest_QuestCharacterS": 321028121,
		"priority": 304
	},
	{
		"ID": 305,
		"name": "フラベルム",
		"quest_QuestCharacterS": 325016121,
		"priority": 305
	},
	{
		"ID": 306,
		"name": "カラドボルグ",
		"quest_QuestCharacterS": 321026121,
		"priority": 306
	},
	{
		"ID": 307,
		"name": "ケーリュケイオン",
		"quest_QuestCharacterS": 326005121,
		"priority": 307
	},
	{
		"ID": 308,
		"name": "セファー",
		"quest_QuestCharacterS": 325021121,
		"priority": 308
	},
	{
		"ID": 309,
		"name": "フラガラッハ",
		"quest_QuestCharacterS": 321010121,
		"priority": 309
	},
	{
		"ID": 310,
		"name": "ヴァジュラ",
		"quest_QuestCharacterS": 325005121,
		"priority": 310
	},
	{
		"ID": 311,
		"name": "イシューリエル",
		"quest_QuestCharacterS": 323014121,
		"priority": 311
	},
	{
		"ID": 312,
		"name": "ピサール",
		"quest_QuestCharacterS": 323020121,
		"priority": 312
	},
	{
		"ID": 313,
		"name": "オティヌス",
		"quest_QuestCharacterS": 324008121,
		"priority": 313
	},
	{
		"ID": 314,
		"name": "ウコンバサラ",
		"quest_QuestCharacterS": 322010121,
		"priority": 314
	},
	{
		"ID": 315,
		"name": "梓弓",
		"quest_QuestCharacterS": 324006121,
		"priority": 315
	},
	{
		"ID": 316,
		"name": "ティルフィング",
		"quest_QuestCharacterS": 321014121,
		"priority": 316
	},
	{
		"ID": 317,
		"name": "カドケウス",
		"quest_QuestCharacterS": 326004121,
		"priority": 317
	},
	{
		"ID": 318,
		"name": "ガンバンテイン",
		"quest_QuestCharacterS": 326002121,
		"priority": 318
	},
	{
		"ID": 319,
		"name": "ダグダ",
		"quest_QuestCharacterS": 322006121,
		"priority": 319
	},
	{
		"ID": 320,
		"name": "パラケルスス",
		"quest_QuestCharacterS": 321013121,
		"priority": 320
	},
	{
		"ID": 321,
		"name": "シユウ",
		"quest_QuestCharacterS": 322019121,
		"priority": 321
	},
	{
		"ID": 322,
		"name": "アフロディーテ",
		"quest_QuestCharacterS": 324013121,
		"priority": 322
	},
	{
		"ID": 323,
		"name": "ムラマサ",
		"quest_QuestCharacterS": 321025121,
		"priority": 323
	},
	{
		"ID": 324,
		"name": "レーヴァティン",
		"quest_QuestCharacterS": 321002121,
		"priority": 324
	},
	{
		"ID": 325,
		"name": "ロンゴミアント",
		"quest_QuestCharacterS": 323010121,
		"priority": 325
	},
	{
		"ID": 326,
		"name": "ヴァナルガンド",
		"quest_QuestCharacterS": 326011121,
		"priority": 326
	},
	{
		"ID": 327,
		"name": "シャルウル",
		"quest_QuestCharacterS": 322007121,
		"priority": 327
	},
	{
		"ID": 328,
		"name": "ブラフマーストラ",
		"quest_QuestCharacterS": 325004121,
		"priority": 328
	},
	{
		"ID": 329,
		"name": "ミストルティン",
		"quest_QuestCharacterS": 326006121,
		"priority": 329
	},
	{
		"ID": 330,
		"name": "トライデント",
		"quest_QuestCharacterS": 323002121,
		"priority": 330
	},
	{
		"ID": 331,
		"name": "デュランダル",
		"quest_QuestCharacterS": 321003121,
		"priority": 331
	},
	{
		"ID": 332,
		"name": "ルーン",
		"quest_QuestCharacterS": 323005121,
		"priority": 332
	},
	{
		"ID": 333,
		"name": "アイムール",
		"quest_QuestCharacterS": 322002121,
		"priority": 333
	},
	{
		"ID": 334,
		"name": "エロース",
		"quest_QuestCharacterS": 324004121,
		"priority": 334
	},
	{
		"ID": 335,
		"name": "雑賀",
		"quest_QuestCharacterS": 325024121,
		"priority": 335
	},
	{
		"ID": 336,
		"name": "アポロン",
		"quest_QuestCharacterS": 324003121,
		"priority": 336
	},
	{
		"ID": 337,
		"name": "アロンダイト",
		"quest_QuestCharacterS": 321007121,
		"priority": 337
	},
	{
		"ID": 338,
		"name": "ナーゲルリング",
		"quest_QuestCharacterS": 321006121,
		"priority": 338
	},
	{
		"ID": 339,
		"name": "マサムネ",
		"quest_QuestCharacterS": 321001121,
		"priority": 339
	},
	{
		"ID": 340,
		"name": "プタハ",
		"quest_QuestCharacterS": 326014121,
		"priority": 340
	},
	{
		"ID": 341,
		"name": "ヴォータン",
		"quest_QuestCharacterS": 323017121,
		"priority": 341
	},
	{
		"ID": 342,
		"name": "レシェフ",
		"quest_QuestCharacterS": 322013121,
		"priority": 342
	},
	{
		"ID": 343,
		"name": "スラーンド",
		"quest_QuestCharacterS": 322012121,
		"priority": 343
	},
	{
		"ID": 344,
		"name": "タスラム",
		"quest_QuestCharacterS": 325020121,
		"priority": 344
	},
	{
		"ID": 345,
		"name": "テュルソス",
		"quest_QuestCharacterS": 326003121,
		"priority": 345
	},
	{
		"ID": 346,
		"name": "青龍偃月刀",
		"quest_QuestCharacterS": 323009121,
		"priority": 346
	},
	{
		"ID": 347,
		"name": "ゲイボルグ",
		"quest_QuestCharacterS": 323007121,
		"priority": 347
	},
	{
		"ID": 348,
		"name": "ワズラ",
		"quest_QuestCharacterS": 322011121,
		"priority": 348
	},
	{
		"ID": 349,
		"name": "フライクーゲル",
		"quest_QuestCharacterS": 325002121,
		"priority": 349
	},
	{
		"ID": 350,
		"name": "ハロウィン_ダモクレス",
		"quest_QuestCharacterS": 310352301,
		"priority": 350
	},
	{
		"ID": 351,
		"name": "ハロウィン_ネス",
		"quest_QuestCharacterS": 360202301,
		"priority": 351
	},
	{
		"ID": 352,
		"name": "学園_トライデント",
		"quest_QuestCharacterS": 330024301,
		"priority": 352
	},
	{
		"ID": 353,
		"name": "学園_フライクーゲル",
		"quest_QuestCharacterS": 350027301,
		"priority": 353
	},
	{
		"ID": 354,
		"name": "学園_ハルパー",
		"quest_QuestCharacterS": 320202301,
		"priority": 354
	},
	{
		"ID": 355,
		"name": "天使_シェキナー",
		"quest_QuestCharacterS": 334007131,
		"priority": 355
	},
	{
		"ID": 356,
		"name": "マサムネ獣刻",
		"quest_QuestCharacterS": 331001131,
		"priority": 356
	},
	{
		"ID": 357,
		"name": "芭蕉扇D.plug",
		"quest_QuestCharacterS": 335008131,
		"priority": 357
	},
	{
		"ID": 358,
		"name": "ツクヨミ",
		"quest_QuestCharacterS": 360221301,
		"priority": 358
	},
	{
		"ID": 359,
		"name": "ヨミ",
		"quest_QuestCharacterS": 340181301,
		"priority": 359
	},
	{
		"ID": 360,
		"name": "天沼矛 聖鎖",
		"quest_QuestCharacterS": 333004131,
		"priority": 360
	},
	{
		"ID": 361,
		"name": "パラケルススD.plug",
		"quest_QuestCharacterS": 331013131,
		"priority": 361
	},
	{
		"ID": 362,
		"name": "アルベル",
		"quest_QuestCharacterS": 350291301,
		"priority": 362
	},
	{
		"ID": 363,
		"name": "ヴァナルガンド・聖鎖・サリエル",
		"quest_QuestCharacterS": 336011131,
		"priority": 363
	},
	{
		"ID": 364,
		"name": "アバリス・D. plug・パズズ",
		"quest_QuestCharacterS": 334010131,
		"priority": 364
	},
	{
		"ID": 365,
		"name": "エルキュール　クリスマスver.",
		"quest_QuestCharacterS": 320252301,
		"priority": 365
	},
	{
		"ID": 366,
		"name": "ミネルヴァ　クリスマスver.",
		"quest_QuestCharacterS": 330252301,
		"priority": 366
	},
	{
		"ID": 367,
		"name": "ケラウノス・獣刻・テュポーン",
		"quest_QuestCharacterS": 335001131,
		"priority": 367
	},
	{
		"ID": 368,
		"name": "ヤグルシ・D. plug・バエル",
		"quest_QuestCharacterS": 332017131,
		"priority": 368
	},
	{
		"ID": 369,
		"name": "ゲイボルグ・獣刻・ケルベロス",
		"quest_QuestCharacterS": 333007131,
		"priority": 369
	},
	{
		"ID": 370,
		"name": "シタ・聖鎖・メタトロン",
		"quest_QuestCharacterS": 332016131,
		"priority": 370
	},
	{
		"ID": 371,
		"name": "ラグナロク",
		"quest_QuestCharacterS": 310362301,
		"priority": 371
	},
	{
		"ID": 372,
		"name": "ティルフィング",
		"quest_QuestCharacterS": 310148301,
		"priority": 372
	},
	{
		"ID": 373,
		"name": "アルマス",
		"quest_QuestCharacterS": 331038131,
		"priority": 373
	},
	{
		"ID": 374,
		"name": "ミョルニル・獣刻・キマイラ",
		"quest_QuestCharacterS": 332001131,
		"priority": 374
	},
	{
		"ID": 375,
		"name": "ミストルティン・獣刻・ドリュアス",
		"quest_QuestCharacterS": 336006131,
		"priority": 375
	},
	{
		"ID": 376,
		"name": "セツナ",
		"quest_QuestCharacterS": 310391301,
		"priority": 376
	},
	{
		"ID": 377,
		"name": "ナーゲルリング",
		"quest_QuestCharacterS": 310066301,
		"priority": 377
	},
	{
		"ID": 378,
		"name": "ロンギヌス",
		"quest_QuestCharacterS": 330019301,
		"priority": 378
	},
	{
		"ID": 379,
		"name": "木之本 桜",
		"quest_QuestCharacterS": 360231301,
		"priority": 379
	},
	{
		"ID": 380,
		"name": "木之本 桜",
		"quest_QuestCharacterS": 360232301,
		"priority": 380
	},
	{
		"ID": 381,
		"name": "フライシュッツ",
		"quest_QuestCharacterS": 350272301,
		"priority": 381
	},
	{
		"ID": 382,
		"name": "グラーシーザ",
		"quest_QuestCharacterS": 330262301,
		"priority": 382
	},
	{
		"ID": 383,
		"name": "木之本 桜",
		"quest_QuestCharacterS": 360233301,
		"priority": 383
	},
	{
		"ID": 384,
		"name": "与一",
		"quest_QuestCharacterS": 340057301,
		"priority": 384
	},
	{
		"ID": 385,
		"name": "アロンダイト・獣刻・ユニコーン",
		"quest_QuestCharacterS": 331007131,
		"priority": 385
	},
	{
		"ID": 386,
		"name": "オティヌス・D. plug・オセ",
		"quest_QuestCharacterS": 334008131,
		"priority": 386
	},
	{
		"ID": 387,
		"name": "モラルタ",
		"quest_QuestCharacterS": 331040122,
		"priority": 387
	},
	{
		"ID": 388,
		"name": "ベガルタ",
		"quest_QuestCharacterS": 331041122,
		"priority": 388
	},
	{
		"ID": 389,
		"name": "雑賀・D. plug・ハルファス",
		"quest_QuestCharacterS": 335024131,
		"priority": 389
	},
	{
		"ID": 390,
		"name": "ラブリュス・聖鎖・カマエル",
		"quest_QuestCharacterS": 332003131,
		"priority": 390
	},
	{
		"ID": 391,
		"name": "カラドボルグ",
		"quest_QuestCharacterS": 310262301,
		"priority": 391
	},
	{
		"ID": 392,
		"name": "クラウ・ソラス",
		"quest_QuestCharacterS": 310272301,
		"priority": 392
	},
	{
		"ID": 393,
		"name": "ガンバンテイン・D. plug・サルガタナス",
		"quest_QuestCharacterS": 336002131,
		"priority": 393
	},
	{
		"ID": 394,
		"name": "梓弓・獣刻・メデューサ",
		"quest_QuestCharacterS": 334006131,
		"priority": 394
	},
	{
		"ID": 395,
		"name": "レーヴァテイン・獣刻・バハムート",
		"quest_QuestCharacterS": 331002131,
		"priority": 395
	},
	{
		"ID": 396,
		"name": "ヘレナ・D. plug・ロキ",
		"quest_QuestCharacterS": 333028131,
		"priority": 396
	},
	{
		"ID": 397,
		"name": "サンゴ",
		"quest_QuestCharacterS": 330291301,
		"priority": 397
	},
	{
		"ID": 398,
		"name": "ルーシャ",
		"quest_QuestCharacterS": 350301301,
		"priority": 398
	},
	{
		"ID": 399,
		"name": "メルリヌス",
		"quest_QuestCharacterS": 360241301,
		"priority": 399
	},
	{
		"ID": 400,
		"name": "カリス・聖鎖・アザゼル",
		"quest_QuestCharacterS": 336025131,
		"priority": 400
	},
	{
		"ID": 401,
		"name": "ピサール・聖鎖・サマエル",
		"quest_QuestCharacterS": 333020131,
		"priority": 401
	},
	{
		"ID": 402,
		"name": "シェキナー　ウェディング",
		"quest_QuestCharacterS": 340077301,
		"priority": 402
	},
	{
		"ID": 403,
		"name": "スイハ　ウェディング",
		"quest_QuestCharacterS": 340172301,
		"priority": 403
	},
	{
		"ID": 404,
		"name": "ムラマサ・獣刻・ヤマタノオロチ",
		"quest_QuestCharacterS": 331025131,
		"priority": 404
	},
	{
		"ID": 405,
		"name": "ロンギヌス・聖鎖・ガブリエル",
		"quest_QuestCharacterS": 333001131,
		"priority": 405
	},
	{
		"ID": 406,
		"name": "ソロモン・聖鎖・アテナ",
		"quest_QuestCharacterS": 335031131,
		"priority": 406
	},
	{
		"ID": 407,
		"name": "ロンゴミアント・D. plug・グラシャラボラス",
		"quest_QuestCharacterS": 333010131,
		"priority": 407
	},
	{
		"ID": 408,
		"name": "アスカロン・D. plug・レヴィアタン",
		"quest_QuestCharacterS": 331023131,
		"priority": 408
	},
	{
		"ID": 409,
		"name": "グリモワール・獣刻・ニーズヘッグ",
		"quest_QuestCharacterS": 335017131,
		"priority": 409
	},
	{
		"ID": 410,
		"name": "フライシュッツ",
		"quest_QuestCharacterS": 321014231,
		"priority": 410
	},
	{
		"ID": 411,
		"name": "ティルフィング",
		"quest_QuestCharacterS": 322004231,
		"priority": 411
	},
	{
		"ID": 412,
		"name": "パラシュ",
		"quest_QuestCharacterS": 325027131,
		"priority": 412
	},
	{
		"ID": 413,
		"name": "めぐみん",
		"quest_QuestCharacterS": 325025131,
		"priority": 413
	},
	{
		"ID": 414,
		"name": "ダクネス",
		"quest_QuestCharacterS": 321034131,
		"priority": 414
	},
	{
		"ID": 415,
		"name": "アルテミス",
		"quest_QuestCharacterS": 324001231,
		"priority": 415
	},
	{
		"ID": 416,
		"name": "ミネルヴァ",
		"quest_QuestCharacterS": 323025131,
		"priority": 416
	},
	{
		"ID": 417,
		"name": "アフロディーテ・D. plug・アスモデウス",
		"quest_QuestCharacterS": 334013131,
		"priority": 417
	},
	{
		"ID": 418,
		"name": "フライクーゲル・聖鎖・アズラエル",
		"quest_QuestCharacterS": 335002131,
		"priority": 418
	},
	{
		"ID": 419,
		"name": "アクア",
		"quest_QuestCharacterS": 326017131,
		"priority": 419
	},
	{
		"ID": 420,
		"name": "ティルフィング",
		"quest_QuestCharacterS": 321014331,
		"priority": 420
	},
	{
		"ID": 421,
		"name": "ラグナロク",
		"quest_QuestCharacterS": 321036131,
		"priority": 421
	},
	{
		"ID": 422,
		"name": "ロンギヌス",
		"quest_QuestCharacterS": 323001231,
		"priority": 422
	},
	{
		"ID": 423,
		"name": "スイハ",
		"quest_QuestCharacterS": 324017131,
		"priority": 423
	},
	{
		"ID": 424,
		"name": "マサムネ",
		"quest_QuestCharacterS": 321001231,
		"priority": 424
	},
	{
		"ID": 425,
		"name": "マサムネ",
		"quest_QuestCharacterS": 321035131,
		"priority": 425
	},
	{
		"ID": 426,
		"name": "エルキュール",
		"quest_QuestCharacterS": 322025131,
		"priority": 426
	},
	{
		"ID": 427,
		"name": "ネス",
		"quest_QuestCharacterS": 326020131,
		"priority": 427
	},
	{
		"ID": 428,
		"name": "レーヴァテイン",
		"quest_QuestCharacterS": 321002231,
		"priority": 428
	},
	{
		"ID": 429,
		"name": "アルテミス・獣刻・マスターテリオン",
		"quest_QuestCharacterS": 334001131,
		"priority": 429
	},
	{
		"ID": 430,
		"name": "パラシュ・D. plug・アスタロス",
		"quest_QuestCharacterS": 332004131,
		"priority": 430
	},
	{
		"ID": 431,
		"name": "フォルカス・聖鎖・ウリエル",
		"quest_QuestCharacterS": 333018131,
		"priority": 431
	},
	{
		"ID": 432,
		"name": "シユウ・D. plug・ベルゼブブ",
		"quest_QuestCharacterS": 332019131,
		"priority": 432
	},
	{
		"ID": 433,
		"name": "グラーシーザ",
		"quest_QuestCharacterS": 323026131,
		"priority": 433
	},
	{
		"ID": 434,
		"name": "フライクーゲル",
		"quest_QuestCharacterS": 325002231,
		"priority": 434
	},
	{
		"ID": 435,
		"name": "エロース",
		"quest_QuestCharacterS": 334004131,
		"priority": 435
	},
	{
		"ID": 436,
		"name": "スラーンド",
		"quest_QuestCharacterS": 332012131,
		"priority": 436
	},
	{
		"ID": 437,
		"name": "モラルタ",
		"quest_QuestCharacterS": 331040731,
		"priority": 437
	},
	{
		"ID": 438,
		"name": "ベガルタ",
		"quest_QuestCharacterS": 331041731,
		"priority": 438
	},
	{
		"ID": 439,
		"name": "デュリン",
		"quest_QuestCharacterS": 32028131,
		"priority": 439
	},
	{
		"ID": 440,
		"name": "リル=ティルフィング",
		"quest_QuestCharacterS": 331014131,
		"priority": 440
	},
	{
		"ID": 441,
		"name": "ティファレト",
		"quest_QuestCharacterS": 335032131,
		"priority": 441
	},
	{
		"ID": 442,
		"name": "ガ・ボー",
		"quest_QuestCharacterS": 333021131,
		"priority": 442
	},
	{
		"ID": 443,
		"name": "アハト",
		"quest_QuestCharacterS": 32027131,
		"priority": 443
	},
	{
		"ID": 444,
		"name": "フィーア",
		"quest_QuestCharacterS": 36026131,
		"priority": 444
	},
	{
		"ID": 445,
		"name": "エミリア",
		"quest_QuestCharacterS": 336027131,
		"priority": 445
	},
	{
		"ID": 446,
		"name": "レム",
		"quest_QuestCharacterS": 332029131,
		"priority": 446
	},
	{
		"ID": 447,
		"name": "ラム",
		"quest_QuestCharacterS": 335033121,
		"priority": 447
	},
	{
		"ID": 448,
		"name": "ラム（幼少期）",
		"quest_QuestCharacterS": 335033221,
		"priority": 448
	},
	{
		"ID": 449,
		"name": "レム（鬼）",
		"quest_QuestCharacterS": 332029221,
		"priority": 449
	},
	{
		"ID": 450,
		"name": "フェイルノート",
		"quest_QuestCharacterS": 334019121,
		"priority": 450
	},
	{
		"ID": 451,
		"name": "グラム",
		"quest_QuestCharacterS": 331008121,
		"priority": 451
	},
	{
		"ID": 452,
		"name": "フォルカス クリスマス",
		"quest_QuestCharacterS": 333018221,
		"priority": 452
	},
	{
		"ID": 453,
		"name": "カリス クリスマス",
		"quest_QuestCharacterS": 336025221,
		"priority": 453
	},
	{
		"ID": 454,
		"name": "バルムンク",
		"quest_QuestCharacterS": 331009121,
		"priority": 454
	},
	{
		"ID": 455,
		"name": "シャルウル",
		"quest_QuestCharacterS": 332007121,
		"priority": 455
	},
	{
		"ID": 456,
		"name": "ソロモン・聖鎖・アテナ 人気投票1位ver.",
		"quest_QuestCharacterS": 335031231,
		"priority": 456
	},
	{
		"ID": 457,
		"name": "アバリス・D. plug・パズズ 賀正ver.",
		"quest_QuestCharacterS": 334010231,
		"priority": 457
	},
	{
		"ID": 458,
		"name": "ガ･ジャルグ・獣刻・イーリス",
		"quest_QuestCharacterS": 333032131,
		"priority": 458
	},
	{
		"ID": 459,
		"name": "カシウス・獣刻・ウロボロス",
		"quest_QuestCharacterS": 333031131,
		"priority": 459
	},
	{
		"ID": 460,
		"name": "天使ミトゥム",
		"quest_QuestCharacterS": 332005121,
		"priority": 460
	},
	{
		"ID": 461,
		"name": "悪魔グリダヴォル",
		"quest_QuestCharacterS": 336008121,
		"priority": 461
	},
	{
		"ID": 462,
		"name": "ヘレナ バレンタイン",
		"quest_QuestCharacterS": 333028221,
		"priority": 462
	},
	{
		"ID": 463,
		"name": "オティヌス バレンタイン",
		"quest_QuestCharacterS": 334008221,
		"priority": 463
	},
	{
		"ID": 464,
		"name": "神令スイハ",
		"quest_QuestCharacterS": 334017121,
		"priority": 464
	},
	{
		"ID": 465,
		"name": "天使ハルパー",
		"quest_QuestCharacterS": 332020121,
		"priority": 465
	},
	{
		"ID": 466,
		"name": "悪魔デュランダル",
		"quest_QuestCharacterS": 331003131,
		"priority": 466
	},
	{
		"ID": 467,
		"name": "悪魔セファー",
		"quest_QuestCharacterS": 335021131,
		"priority": 467
	},
	{
		"ID": 468,
		"name": "ロフィア",
		"quest_QuestCharacterS": 36028131,
		"priority": 468
	},
	{
		"ID": 469,
		"name": "天使エクスカリバー",
		"quest_QuestCharacterS": 331011131,
		"priority": 469
	},
	{
		"ID": 470,
		"name": "幻獣与一",
		"quest_QuestCharacterS": 334005131,
		"priority": 470
	},
	{
		"ID": 471,
		"name": "神令フライシュッツ",
		"quest_QuestCharacterS": 335027131,
		"priority": 471
	},
	{
		"ID": 472,
		"name": "ダモクレス・神令・ヘル",
		"quest_QuestCharacterS": 331035131,
		"priority": 472
	},
	{
		"ID": 473,
		"name": "イシューリエル・D. plug・マルコシアス",
		"quest_QuestCharacterS": 336004131,
		"priority": 473
	},
	{
		"ID": 474,
		"name": "カドケウス・獣刻・ムニン",
		"quest_QuestCharacterS": 333014131,
		"priority": 474
	},
	{
		"ID": 475,
		"name": "木之本 桜OP2",
		"quest_QuestCharacterS": 360234131,
		"priority": 475
	},
	{
		"ID": 476,
		"name": "神令エルキュール",
		"quest_QuestCharacterS": 332025131,
		"priority": 476
	},
	{
		"ID": 477,
		"name": "でんぱ",
		"quest_QuestCharacterS": 331018131,
		"priority": 477
	},
	{
		"ID": 478,
		"name": "シユウ イースター",
		"quest_QuestCharacterS": 332019231,
		"priority": 478
	},
	{
		"ID": 479,
		"name": "ヴァナルガンド イースター",
		"quest_QuestCharacterS": 336011231,
		"priority": 479
	},
	{
		"ID": 480,
		"name": "グラーシーザ・神令・フォルセティ",
		"quest_QuestCharacterS": 333026131,
		"priority": 480
	},
	{
		"ID": 481,
		"name": "ナーゲルリング・聖鎖・ラグエル",
		"quest_QuestCharacterS": 331006131,
		"priority": 481
	},
	{
		"ID": 482,
		"name": "悪魔方天画戟",
		"quest_QuestCharacterS": 333003131,
		"priority": 482
	},
	{
		"ID": 483,
		"name": "神令ミネルヴァ",
		"quest_QuestCharacterS": 333025131,
		"priority": 483
	},
	{
		"ID": 484,
		"name": "エミリア　ウェディング",
		"quest_QuestCharacterS": 336027231,
		"priority": 484
	},
	{
		"ID": 485,
		"name": "ネス・神令・スクルド",
		"quest_QuestCharacterS": 336020131,
		"priority": 485
	},
	{
		"ID": 486,
		"name": "八咫鏡・獣刻・ジャバウォック",
		"quest_QuestCharacterS": 335003131,
		"priority": 486
	},
	{
		"ID": 487,
		"name": "ラム ウェディングver",
		"quest_QuestCharacterS": 335033331,
		"priority": 487
	},
	{
		"ID": 488,
		"name": "ラグナロク・神令・ユグドラシル",
		"quest_QuestCharacterS": 331036131,
		"priority": 488
	},
	{
		"ID": 489,
		"name": "レム",
		"quest_QuestCharacterS": 332029331,
		"priority": 489
	},
	{
		"ID": 490,
		"name": "メラ",
		"quest_QuestCharacterS": 35034131,
		"priority": 490
	},
	{
		"ID": 491,
		"name": "ソロモン・聖鎖・アテナ ウェディングver.",
		"quest_QuestCharacterS": 335031331,
		"priority": 491
	},
	{
		"ID": 492,
		"name": "タスラム・獣刻・バンシー",
		"quest_QuestCharacterS": 335020131,
		"priority": 492
	},
	{
		"ID": 493,
		"name": "ロンギヌス・聖鎖・ガブリエル ウェディングver.",
		"quest_QuestCharacterS": 333001231,
		"priority": 493
	},
	{
		"ID": 494,
		"name": "ダグダ・獣刻・ベヒモス",
		"quest_QuestCharacterS": 332006131,
		"priority": 494
	},
	{
		"ID": 495,
		"name": "アルマス・妖精結合・ティターニア 海上編ver.",
		"quest_QuestCharacterS": 321038131,
		"priority": 495
	},
	{
		"ID": 496,
		"name": "ソロモン",
		"quest_QuestCharacterS": 35031131,
		"priority": 496
	},
	{
		"ID": 497,
		"name": "ティファレト・聖鎖・ミカエル 海上編ver.",
		"quest_QuestCharacterS": 325032131,
		"priority": 497
	},
	{
		"ID": 498,
		"name": "リサナウト・針枷・クロノス",
		"quest_QuestCharacterS": 332030131,
		"priority": 498
	},
	{
		"ID": 499,
		"name": "リットゥ・D. plug・ナベリウス",
		"quest_QuestCharacterS": 331005131,
		"priority": 499
	},
	{
		"ID": 500,
		"name": "ケーリュケイオン・獣刻・フギン",
		"quest_QuestCharacterS": 336005131,
		"priority": 500
	},
	{
		"ID": 501,
		"name": "ヘレナ・D. plug・ロキ",
		"quest_QuestCharacterS": 323028131,
		"priority": 501
	},
	{
		"ID": 502,
		"name": "フェイルノート・D. plug・ルシファー",
		"quest_QuestCharacterS": 324019131,
		"priority": 502
	},
	{
		"ID": 503,
		"name": "モラベガ・妖精結合・ピスカ",
		"quest_QuestCharacterS": 331042131,
		"priority": 503
	},
	{
		"ID": 504,
		"name": "ガ・ジャルグ・獣刻・イーリス",
		"quest_QuestCharacterS": 323032131,
		"priority": 504
	},
	{
		"ID": 505,
		"name": "アイムール・D. plug・モート",
		"quest_QuestCharacterS": 332002131,
		"priority": 505
	},
	{
		"ID": 506,
		"name": "シストルム・獣刻・バステト",
		"quest_QuestCharacterS": 336013131,
		"priority": 506
	},
	{
		"ID": 507,
		"name": "ウィズ",
		"quest_QuestCharacterS": 326018131,
		"priority": 507
	},
	{
		"ID": 508,
		"name": "ゆんゆん",
		"quest_QuestCharacterS": 325026131,
		"priority": 508
	},
	{
		"ID": 509,
		"name": "ソロモン・聖鎖・アテナ",
		"quest_QuestCharacterS": 325031131,
		"priority": 509
	},
	{
		"ID": 510,
		"name": "レーヴァテイン・獣刻・バハムート",
		"quest_QuestCharacterS": 321002331,
		"priority": 510
	},
	{
		"ID": 511,
		"name": "カシウス・獣刻・ウロボロス",
		"quest_QuestCharacterS": 323031131,
		"priority": 511
	},
	{
		"ID": 512,
		"name": "モラベガ",
		"quest_QuestCharacterS": 321042131,
		"priority": 512
	},
	{
		"ID": 513,
		"name": "カリス・聖鎖・アザゼル",
		"quest_QuestCharacterS": 326025131,
		"priority": 513
	},
	{
		"ID": 514,
		"name": "ブリューナク",
		"quest_QuestCharacterS": 335007131,
		"priority": 514
	},
	{
		"ID": 515,
		"name": "蜻蛉切・聖鎖・インドラ",
		"quest_QuestCharacterS": 333024131,
		"priority": 515
	},
	{
		"ID": 516,
		"name": "アロンダイト・獣刻・ユニコーン",
		"quest_QuestCharacterS": 331007231,
		"priority": 516
	},
	{
		"ID": 517,
		"name": "マサムネ・獣刻・ヨルムンガンド",
		"quest_QuestCharacterS": 331001231,
		"priority": 517
	},
	{
		"ID": 518,
		"name": "ピナーカ・獣刻・ガルーダ",
		"quest_QuestCharacterS": 334002131,
		"priority": 518
	},
	{
		"ID": 519,
		"name": "レシェフ・獣刻・ネルガル",
		"quest_QuestCharacterS": 332013131,
		"priority": 519
	},
	{
		"ID": 520,
		"name": "ティルフィング・擬彩",
		"quest_QuestCharacterS": 351014331,
		"priority": 520
	},
	{
		"ID": 521,
		"name": "アルマス・擬彩",
		"quest_QuestCharacterS": 351038331,
		"priority": 521
	},
	{
		"ID": 522,
		"name": "ティルフィング",
		"quest_QuestCharacterS": 310149301,
		"priority": 522
	},
	{
		"ID": 523,
		"name": "カヤ",
		"quest_QuestCharacterS": 350351301,
		"priority": 523
	},
	{
		"ID": 524,
		"name": "鹿目 まどか",
		"quest_QuestCharacterS": 334011131,
		"priority": 524
	},
	{
		"ID": 525,
		"name": "フライクーゲル",
		"quest_QuestCharacterS": 355002331,
		"priority": 525
	},
	{
		"ID": 526,
		"name": "巴 マミ",
		"quest_QuestCharacterS": 335014131,
		"priority": 526
	},
	{
		"ID": 527,
		"name": "エンメル",
		"quest_QuestCharacterS": 360291301,
		"priority": 527
	},
	{
		"ID": 528,
		"name": "アルテミス・疑彩",
		"quest_QuestCharacterS": 354001331,
		"priority": 528
	},
	{
		"ID": 529,
		"name": "美樹 さやか",
		"quest_QuestCharacterS": 331020131,
		"priority": 529
	},
	{
		"ID": 530,
		"name": "暁美 ほむら",
		"quest_QuestCharacterS": 335013131,
		"priority": 530
	},
	{
		"ID": 531,
		"name": "佐倉 杏子",
		"quest_QuestCharacterS": 333015131,
		"priority": 531
	},
	{
		"ID": 532,
		"name": "ロンギヌス・擬彩",
		"quest_QuestCharacterS": 353001331,
		"priority": 532
	},
	{
		"ID": 533,
		"name": "リサナウト・針枷・クロノス",
		"quest_QuestCharacterS": 332030231,
		"priority": 533
	},
	{
		"ID": 534,
		"name": "グリモワール・獣刻・ニーズヘッグ",
		"quest_QuestCharacterS": 335017231,
		"priority": 534
	},
	{
		"ID": 535,
		"name": "スイハ・擬装・セイバー",
		"quest_QuestCharacterS": 354017231,
		"priority": 535
	},
	{
		"ID": 536,
		"name": "ペルーン・聖鎖・マスティマ",
		"quest_QuestCharacterS": 332008131,
		"priority": 536
	},
	{
		"ID": 537,
		"name": "ティファレト・聖鎖・ミカエル　賀正ver.",
		"quest_QuestCharacterS": 335032231,
		"priority": 537
	},
	{
		"ID": 538,
		"name": "カシウス・獣刻・ウロボロス人気投票ver.",
		"quest_QuestCharacterS": 333031231,
		"priority": 538
	},
	{
		"ID": 539,
		"name": "マサムネ・擬彩",
		"quest_QuestCharacterS": 351001331,
		"priority": 539
	},
	{
		"ID": 540,
		"name": "パラシュ・擬彩",
		"quest_QuestCharacterS": 352004331,
		"priority": 540
	},
	{
		"ID": 541,
		"name": "マサムネ(キラーメイル)",
		"quest_QuestCharacterS": 311001131,
		"priority": 541
	},
	{
		"ID": 542,
		"name": "フライシュッツ・擬装・ランサー",
		"quest_QuestCharacterS": 355027231,
		"priority": 542
	},
	{
		"ID": 543,
		"name": "レーヴァテイン・擬彩",
		"quest_QuestCharacterS": 351002331,
		"priority": 543
	},
	{
		"ID": 544,
		"name": "フェイルノート・D. plug・ルシファー",
		"quest_QuestCharacterS": 334019231,
		"priority": 544
	},
	{
		"ID": 545,
		"name": "アスカロン・D. plug・レヴィアタン",
		"quest_QuestCharacterS": 331023231,
		"priority": 545
	},
	{
		"ID": 546,
		"name": "ヒョウハ・神令・テュール",
		"quest_QuestCharacterS": 354020131,
		"priority": 546
	},
	{
		"ID": 547,
		"name": "フォルカス・神令・ヘル",
		"quest_QuestCharacterS": 353018131,
		"priority": 547
	},
	{
		"ID": 548,
		"name": "ミョルニル(キラーメイル)",
		"quest_QuestCharacterS": 351200131,
		"priority": 548
	},
	{
		"ID": 549,
		"name": "アスクレピオス(キラーメイル)",
		"quest_QuestCharacterS": 351600131,
		"priority": 549
	},
	{
		"ID": 550,
		"name": "ツヴァイ",
		"quest_QuestCharacterS": 360301301,
		"priority": 550
	},
	{
		"ID": 551,
		"name": "ダモクレス・擬装・プリースト",
		"quest_QuestCharacterS": 351035231,
		"priority": 551
	},
	{
		"ID": 552,
		"name": "ズィーヴァ",
		"quest_QuestCharacterS": 310431131,
		"priority": 552
	},
	{
		"ID": 553,
		"name": "ロジェスティラ・神令・スクルド",
		"quest_QuestCharacterS": 355037131,
		"priority": 553
	},
	{
		"ID": 554,
		"name": "アポロン(キラーメイル)",
		"quest_QuestCharacterS": 351400331,
		"priority": 554
	},
	{
		"ID": 555,
		"name": "アルテミス(キラーメイル)",
		"quest_QuestCharacterS": 351400131,
		"priority": 555
	},
	{
		"ID": 556,
		"name": "ヘスティア",
		"quest_QuestCharacterS": 336031131,
		"priority": 556
	},
	{
		"ID": 557,
		"name": "ヘスティア　バイト",
		"quest_QuestCharacterS": 336031231,
		"priority": 557
	},
	{
		"ID": 558,
		"name": "アイズ・ヴァレンシュタイン",
		"quest_QuestCharacterS": 331044131,
		"priority": 558
	},
	{
		"ID": 559,
		"name": "リュー・リオン",
		"quest_QuestCharacterS": 331045131,
		"priority": 559
	},
	{
		"ID": 560,
		"name": "エルキュール・擬装・セイバー",
		"quest_QuestCharacterS": 352025231,
		"priority": 560
	},
	{
		"ID": 561,
		"name": "リリルカ・アーデ",
		"quest_QuestCharacterS": 334021131,
		"priority": 561
	},
	{
		"ID": 562,
		"name": "サンジョウノ・春姫",
		"quest_QuestCharacterS": 335036131,
		"priority": 562
	},
	{
		"ID": 563,
		"name": "アルマス・妖精結合・ティターニア",
		"quest_QuestCharacterS": 331038231,
		"priority": 563
	},
	{
		"ID": 564,
		"name": "モラベガ・妖精結合・ピスカ",
		"quest_QuestCharacterS": 331042231,
		"priority": 564
	},
	{
		"ID": 565,
		"name": "メギド",
		"quest_QuestCharacterS": 350062301,
		"priority": 565
	},
	{
		"ID": 566,
		"name": "プタハ・D. plug・ブエル",
		"quest_QuestCharacterS": 336014131,
		"priority": 566
	},
	{
		"ID": 567,
		"name": "オルフェウス・神令・フォルセティ",
		"quest_QuestCharacterS": 356032131,
		"priority": 567
	},
	{
		"ID": 568,
		"name": "ヴォータン・獣刻・スレイプニル",
		"quest_QuestCharacterS": 333017131,
		"priority": 568
	},
	{
		"ID": 569,
		"name": "テュルソス・D. plug・フォルネウス",
		"quest_QuestCharacterS": 336003131,
		"priority": 569
	},
	{
		"ID": 570,
		"name": "グラーシーザ・擬装・ウォーリアー",
		"quest_QuestCharacterS": 353026231,
		"priority": 570
	},
	{
		"ID": 571,
		"name": "アフロディーテ・D. plug・アスモデウス",
		"quest_QuestCharacterS": 354013131,
		"priority": 571
	},
	{
		"ID": 572,
		"name": "ヴァナルガンド・聖鎖・サリエル",
		"quest_QuestCharacterS": 356011131,
		"priority": 572
	},
	{
		"ID": 573,
		"name": "ミネルヴァ・擬装・アーチャー",
		"quest_QuestCharacterS": 353025231,
		"priority": 573
	},
	{
		"ID": 574,
		"name": "如意金箍棒・神令・フリッグ",
		"quest_QuestCharacterS": 352031131,
		"priority": 574
	},
	{
		"ID": 575,
		"name": "ネス・擬装・ランサー",
		"quest_QuestCharacterS": 356020231,
		"priority": 575
	},
	{
		"ID": 576,
		"name": "ミュルグレス・神令・トール",
		"quest_QuestCharacterS": 351046131,
		"priority": 576
	},
	{
		"ID": 577,
		"name": "ムラマサ・獣刻・ヤマタノオロチ",
		"quest_QuestCharacterS": 351025131,
		"priority": 577
	},
	{
		"ID": 578,
		"name": "グングニル・D. plug・アモン",
		"quest_QuestCharacterS": 333008131,
		"priority": 578
	},
	{
		"ID": 579,
		"name": "イチイバル・神令・オーディン",
		"quest_QuestCharacterS": 354022131,
		"priority": 579
	},
	{
		"ID": 580,
		"name": "カシウス・獣刻・ウロボロス",
		"quest_QuestCharacterS": 333031331,
		"priority": 580
	},
	{
		"ID": 581,
		"name": "シユウ・D. plug・ベルゼブブ",
		"quest_QuestCharacterS": 352019131,
		"priority": 581
	},
	{
		"ID": 582,
		"name": "レーヴァテイン・獣刻・バハムート",
		"quest_QuestCharacterS": 331002231,
		"priority": 582
	},
	{
		"ID": 583,
		"name": "ウコンバサラ",
		"quest_QuestCharacterS": 320102131,
		"priority": 583
	},
	{
		"ID": 584,
		"name": "フォルカス・神令・ヘル",
		"quest_QuestCharacterS": 323018231,
		"priority": 584
	},
	{
		"ID": 585,
		"name": "如意金箍棒・神令・フリッグ",
		"quest_QuestCharacterS": 322031131,
		"priority": 585
	},
	{
		"ID": 586,
		"name": "ソロモン・聖鎖・アテナ",
		"quest_QuestCharacterS": 325031231,
		"priority": 586
	},
	{
		"ID": 587,
		"name": "ティルフィング",
		"quest_QuestCharacterS": 321014431,
		"priority": 587
	},
	{
		"ID": 588,
		"name": "レーヴァテイン",
		"quest_QuestCharacterS": 321002431,
		"priority": 588
	},
	{
		"ID": 589,
		"name": "ヒョウハ・神令・テュール",
		"quest_QuestCharacterS": 324020131,
		"priority": 589
	},
	{
		"ID": 590,
		"name": "カシウス・獣刻・ウロボロス",
		"quest_QuestCharacterS": 323031231,
		"priority": 590
	},
	{
		"ID": 591,
		"name": "ミュルグレス・神令・トール",
		"quest_QuestCharacterS": 321046131,
		"priority": 591
	},
	{
		"ID": 592,
		"name": "リサナウト・針枷・クロノス",
		"quest_QuestCharacterS": 322030131,
		"priority": 592
	},
	{
		"ID": 593,
		"name": "グリモワール・獣刻・ニーズヘッグ",
		"quest_QuestCharacterS": 355017131,
		"priority": 593
	},
	{
		"ID": 594,
		"name": "フラベルム",
		"quest_QuestCharacterS": 350162131,
		"priority": 594
	},
	{
		"ID": 595,
		"name": "ロンギヌス",
		"quest_QuestCharacterS": 323001331,
		"priority": 595
	},
	{
		"ID": 596,
		"name": "オルフェウス・神令・フォルセティ",
		"quest_QuestCharacterS": 326032131,
		"priority": 596
	},
	{
		"ID": 597,
		"name": "アスカロン・D. plug・レヴィアタン",
		"quest_QuestCharacterS": 351023131,
		"priority": 597
	},
	{
		"ID": 598,
		"name": "ロジェスティラ・神令・スクルド 海上編ver.",
		"quest_QuestCharacterS": 325037131,
		"priority": 598
	},
	{
		"ID": 599,
		"name": "鹿目 まどか",
		"quest_QuestCharacterS": 324011131,
		"priority": 599
	},
	{
		"ID": 600,
		"name": "巴 マミ",
		"quest_QuestCharacterS": 325014131,
		"priority": 600
	},
	{
		"ID": 601,
		"name": "美樹 さやか",
		"quest_QuestCharacterS": 321020131,
		"priority": 601
	},
	{
		"ID": 602,
		"name": "暁美 ほむら",
		"quest_QuestCharacterS": 325013131,
		"priority": 602
	},
	{
		"ID": 603,
		"name": "佐倉 杏子",
		"quest_QuestCharacterS": 323015131,
		"priority": 603
	},
	{
		"ID": 604,
		"name": "イチイバル・神令・オーディン 海上編ver.",
		"quest_QuestCharacterS": 324022131,
		"priority": 604
	},
	{
		"ID": 605,
		"name": "パラシュ・D. plug・アスタロス ハロウィンver.",
		"quest_QuestCharacterS": 332004231,
		"priority": 605
	},
	{
		"ID": 606,
		"name": "アルテミス・獣刻・マスターテリオン ハロウィンver.",
		"quest_QuestCharacterS": 334001231,
		"priority": 606
	},
	{
		"ID": 607,
		"name": "カラドボルグ・聖鎖・レリエル",
		"quest_QuestCharacterS": 331026131,
		"priority": 607
	},
	{
		"ID": 608,
		"name": "ダーインスレイヴ・聖鎖・マリク",
		"quest_QuestCharacterS": 331028131,
		"priority": 608
	},
	{
		"ID": 609,
		"name": "ラグナロク・擬装・ガンナー",
		"quest_QuestCharacterS": 351036231,
		"priority": 609
	},
	{
		"ID": 610,
		"name": "フューリー",
		"quest_QuestCharacterS": 36033131,
		"priority": 610
	},
	{
		"ID": 611,
		"name": "アルマス",
		"quest_QuestCharacterS": 331038331,
		"priority": 611
	},
	{
		"ID": 612,
		"name": "ティルフィング・リンク・エイレーネ",
		"quest_QuestCharacterS": 331014231,
		"priority": 612
	},
	{
		"ID": 613,
		"name": "ティファレト・誓約・ミカエル",
		"quest_QuestCharacterS": 355032131,
		"priority": 613
	},
	{
		"ID": 614,
		"name": "戦場ヶ原 ひたぎ",
		"quest_QuestCharacterS": 351047131,
		"priority": 614
	},
	{
		"ID": 615,
		"name": "八九寺 真宵",
		"quest_QuestCharacterS": 356034131,
		"priority": 615
	},
	{
		"ID": 616,
		"name": "千石 撫子",
		"quest_QuestCharacterS": 355038131,
		"priority": 616
	},
	{
		"ID": 617,
		"name": "羽川 翼",
		"quest_QuestCharacterS": 353033131,
		"priority": 617
	},
	{
		"ID": 618,
		"name": "忍野 忍",
		"quest_QuestCharacterS": 351048131,
		"priority": 619
	},
	{
		"ID": 619,
		"name": "神原 駿河",
		"quest_QuestCharacterS": 352032131,
		"priority": 618
	},
	{
		"ID": 620,
		"name": "フェイルノート・誓約・ルシファー",
		"quest_QuestCharacterS": 354019131,
		"priority": 620
	},
	{
		"ID": 621,
		"name": "ヴァジュラ・獣刻・ラクシュミー",
		"quest_QuestCharacterS": 335005131,
		"priority": 621
	},
	{
		"ID": 622,
		"name": "シタ・聖鎖・メタトロン クリスマスver.",
		"quest_QuestCharacterS": 332016231,
		"priority": 622
	},
	{
		"ID": 623,
		"name": "シェキナー・聖鎖・ラファエル クリスマスver.",
		"quest_QuestCharacterS": 334007231,
		"priority": 623
	},
	{
		"ID": 624,
		"name": "オルフェウス",
		"quest_QuestCharacterS": 36032131,
		"priority": 624
	},
	{
		"ID": 625,
		"name": "カシウス・誓約・ウロボロス",
		"quest_QuestCharacterS": 353031131,
		"priority": 625
	},
	{
		"ID": 626,
		"name": "フライクーゲル・聖鎖・アズラエル 賀正ver.",
		"quest_QuestCharacterS": 335002231,
		"priority": 626
	},
	{
		"ID": 627,
		"name": "天沼矛",
		"quest_QuestCharacterS": 351300433,
		"priority": 627
	},
	{
		"ID": 628,
		"name": "デュランダル",
		"quest_QuestCharacterS": 351100343,
		"priority": 628
	},
	{
		"ID": 629,
		"name": "イージス・冥令・ヘル",
		"quest_QuestCharacterS": 352000113,
		"priority": 629
	},
	{
		"ID": 630,
		"name": "フラガラッハ・聖鎖・イオフィエル",
		"quest_QuestCharacterS": 331010131,
		"priority": 630
	},
	{
		"ID": 631,
		"name": "ルーン・獣刻・ヒュドラー",
		"quest_QuestCharacterS": 333005131,
		"priority": 631
	},
	{
		"ID": 632,
		"name": "クシナダ",
		"quest_QuestCharacterS": 356035131,
		"priority": 632
	},
	{
		"ID": 633,
		"name": "ラグナロク",
		"quest_QuestCharacterS": 351036331,
		"priority": 633
	},
	{
		"ID": 634,
		"name": "如意金箍棒・神令・フリッグ",
		"quest_QuestCharacterS": 352031231,
		"priority": 634
	},
	{
		"ID": 635,
		"name": "ヒョウハ・神令・テュール",
		"quest_QuestCharacterS": 354020231,
		"priority": 635
	},
	{
		"ID": 636,
		"name": "ロンギヌス ブラックキラーズ執行官衣装ver.",
		"quest_QuestCharacterS": 353001431,
		"priority": 636
	},
	{
		"ID": 637,
		"name": "トライデント・獣刻・ペガサス",
		"quest_QuestCharacterS": 333002131,
		"priority": 637
	},
	{
		"ID": 638,
		"name": "ネロ",
		"quest_QuestCharacterS": 356036131,
		"priority": 638
	},
	{
		"ID": 639,
		"name": "ダフネ",
		"quest_QuestCharacterS": 352000213,
		"priority": 639
	},
	{
		"ID": 640,
		"name": "カリス・聖鎖・アザゼル",
		"quest_QuestCharacterS": 356025131,
		"priority": 640
	},
	{
		"ID": 641,
		"name": "ティルフィング ブラックキラーズ執行官衣装ver.",
		"quest_QuestCharacterS": 351014131,
		"priority": 641
	},
	{
		"ID": 642,
		"name": "アロンダイト",
		"quest_QuestCharacterS": 351007131,
		"priority": 642
	},
	{
		"ID": 643,
		"name": "リサナウト",
		"quest_QuestCharacterS": 32030131,
		"priority": 643
	},
	{
		"ID": 644,
		"name": "ブラフマーストラ・聖鎖・アリエル",
		"quest_QuestCharacterS": 335004131,
		"priority": 644
	},
	{
		"ID": 645,
		"name": "ヘレナ・D. plug・ロキ",
		"quest_QuestCharacterS": 353028131,
		"priority": 645
	},
	{
		"ID": 646,
		"name": "ネス",
		"quest_QuestCharacterS": 356020331,
		"priority": 646
	},
	{
		"ID": 647,
		"name": "ミネルヴァ",
		"quest_QuestCharacterS": 353025331,
		"priority": 647
	},
	{
		"ID": 648,
		"name": "ロンゴミアント・暴走",
		"quest_QuestCharacterS": 353010131,
		"priority": 648
	},
	{
		"ID": 649,
		"name": "クラウ・ソラス・D. plug・ベリアル",
		"quest_QuestCharacterS": 331027131,
		"priority": 649
	},
	{
		"ID": 650,
		"name": "盤古",
		"quest_QuestCharacterS": 352022131,
		"priority": 650
	},
	{
		"ID": 651,
		"name": "レーヴァテイン・擬彩",
		"quest_QuestCharacterS": 351002431,
		"priority": 651
	},
	{
		"ID": 652,
		"name": "立花響",
		"quest_QuestCharacterS": 353035131,
		"priority": 652
	},
	{
		"ID": 653,
		"name": "小日向未来",
		"quest_QuestCharacterS": 356037131,
		"priority": 653
	},
	{
		"ID": 654,
		"name": "雪音クリス",
		"quest_QuestCharacterS": 354023131,
		"priority": 654
	},
	{
		"ID": 655,
		"name": "ソロモン・聖鎖・アテナ",
		"quest_QuestCharacterS": 355031131,
		"priority": 655
	},
	{
		"ID": 656,
		"name": "オティヌス・暴走",
		"quest_QuestCharacterS": 354008131,
		"priority": 656
	},
	{
		"ID": 657,
		"name": "グランテピエ・獣刻・バハムート",
		"quest_QuestCharacterS": 353034131,
		"priority": 657
	},
	{
		"ID": 658,
		"name": "イチイバル",
		"quest_QuestCharacterS": 354022231,
		"priority": 658
	},
	{
		"ID": 659,
		"name": "ラキナ",
		"quest_QuestCharacterS": 351049131,
		"priority": 659
	},
	{
		"ID": 660,
		"name": "ロジェスティラ・神令・スクルド",
		"quest_QuestCharacterS": 355037231,
		"priority": 660
	},
	{
		"ID": 661,
		"name": "アハト",
		"quest_QuestCharacterS": 352027131,
		"priority": 661
	},
	{
		"ID": 662,
		"name": "ラブリュス・暴走",
		"quest_QuestCharacterS": 352003131,
		"priority": 662
	},
	{
		"ID": 663,
		"name": "ティファレト・誓約・ミカエル",
		"quest_QuestCharacterS": 325032231,
		"priority": 663
	},
	{
		"ID": 664,
		"name": "リサナウト・誓約・クロノス",
		"quest_QuestCharacterS": 352030131,
		"priority": 664
	},
	{
		"ID": 665,
		"name": "イージス・冥令・ヘル ",
		"quest_QuestCharacterS": 322000131,
		"priority": 665
	},
	{
		"ID": 666,
		"name": "盤古",
		"quest_QuestCharacterS": 322022131,
		"priority": 666
	},
	{
		"ID": 667,
		"name": "フェイルノート・誓約・ルシファー",
		"quest_QuestCharacterS": 324019231,
		"priority": 667
	},
	{
		"ID": 668,
		"name": "アルマス・誓約・ティターニア",
		"quest_QuestCharacterS": 351038131,
		"priority": 668
	},
	{
		"ID": 669,
		"name": "グランテピエ・獣刻・バハムート",
		"quest_QuestCharacterS": 323034131,
		"priority": 669
	},
	{
		"ID": 670,
		"name": "スイハ・擬装・セイバー",
		"quest_QuestCharacterS": 354017331,
		"priority": 670
	},
	{
		"ID": 671,
		"name": "ギャラルホルン",
		"quest_QuestCharacterS": 352000331,
		"priority": 671
	},
	{
		"ID": 672,
		"name": "カシウス・誓約・ウロボロス",
		"quest_QuestCharacterS": 323031331,
		"priority": 672
	},
	{
		"ID": 673,
		"name": "ワズラ・D. plug・フールフール",
		"quest_QuestCharacterS": 332011131,
		"priority": 673
	},
	{
		"ID": 674,
		"name": "アルテミス",
		"quest_QuestCharacterS": 354001131,
		"priority": 674
	},
	{
		"ID": 675,
		"name": "ねも",
		"quest_QuestCharacterS": 354024131,
		"priority": 675
	},
	{
		"ID": 676,
		"name": "フリズスキャールヴ",
		"quest_QuestCharacterS": 352004131,
		"priority": 676
	},
	{
		"ID": 677,
		"name": "オルフェウス・神令・フォルセティ",
		"quest_QuestCharacterS": 356032231,
		"priority": 677
	},
	{
		"ID": 678,
		"name": "ぺろりん",
		"quest_QuestCharacterS": 355039131,
		"priority": 678
	},
	{
		"ID": 679,
		"name": "ミュルグレス・神令・トール",
		"quest_QuestCharacterS": 351046231,
		"priority": 679
	},
	{
		"ID": 680,
		"name": "グレイプニル",
		"quest_QuestCharacterS": 352005131,
		"priority": 680
	},
	{
		"ID": 681,
		"name": "アルマス",
		"quest_QuestCharacterS": 351038431,
		"priority": 681
	},
	{
		"ID": 682,
		"name": "ティルフィング feat. はじまりの花に囲まれて",
		"quest_QuestCharacterS": 361014131,
		"priority": 682
	},
	{
		"ID": 683,
		"name": "ユグドラシル・誓約・キラーズ",
		"quest_QuestCharacterS": 352006131,
		"priority": 683
	},
	{
		"ID": 684,
		"name": "セツナ",
		"quest_QuestCharacterS": 31039221,
		"priority": 684
	},
	{
		"ID": 685,
		"name": "トライデント",
		"quest_QuestCharacterS": 33002221,
		"priority": 685
	},
	{
		"ID": 686,
		"name": "メラ",
		"quest_QuestCharacterS": 35034231,
		"priority": 686
	},
	{
		"ID": 687,
		"name": "青龍偃月刀・聖鎖・ザドキエル",
		"quest_QuestCharacterS": 333009131,
		"priority": 687
	},
	{
		"ID": 688,
		"name": "エルキュール・擬装・セイバー",
		"quest_QuestCharacterS": 352025331,
		"priority": 688
	},
	{
		"ID": 689,
		"name": "アダマス・D. plug・アイム",
		"quest_QuestCharacterS": 331012131,
		"priority": 689
	},
	{
		"ID": 690,
		"name": "インテリジェントなスーパーAI キズナアイ",
		"quest_QuestCharacterS": 352007131,
		"priority": 690
	},
	{
		"ID": 691,
		"name": "キズナアイ",
		"quest_QuestCharacterS": 352007231,
		"priority": 691
	},
	{
		"ID": 692,
		"name": "ブラックアイ",
		"quest_QuestCharacterS": 352008131,
		"priority": 692
	},
	{
		"ID": 693,
		"name": "めぐみん",
		"quest_QuestCharacterS": 355025131,
		"priority": 693
	},
	{
		"ID": 694,
		"name": "フェイルノート・誓約・ルシファー",
		"quest_QuestCharacterS": 354019231,
		"priority": 694
	},
	{
		"ID": 695,
		"name": "草薙剣・獣刻・ヴリトラ",
		"quest_QuestCharacterS": 331004131,
		"priority": 695
	},
	{
		"ID": 696,
		"name": "シラサギ",
		"quest_QuestCharacterS": 353036131,
		"priority": 696
	},
	{
		"ID": 697,
		"name": "アマテラス",
		"quest_QuestCharacterS": 353027131,
		"priority": 697
	},
	{
		"ID": 698,
		"name": "イージス・冥令・ヘル",
		"quest_QuestCharacterS": 352000131,
		"priority": 698
	},
	{
		"ID": 699,
		"name": "軍服メイドVtuber 神楽めあ",
		"quest_QuestCharacterS": 351050131,
		"priority": 699
	},
	{
		"ID": 700,
		"name": "神樂めあ",
		"quest_QuestCharacterS": 351050231,
		"priority": 700
	},
	{
		"ID": 701,
		"name": "男の娘系Vtuber 犬山たまき",
		"quest_QuestCharacterS": 353037131,
		"priority": 701
	},
	{
		"ID": 702,
		"name": "犬山たまき",
		"quest_QuestCharacterS": 353037231,
		"priority": 702
	},
	{
		"ID": 703,
		"name": "ウコンバサラ・D. plug・ヴィネ",
		"quest_QuestCharacterS": 332010131,
		"priority": 703
	},
	{
		"ID": 704,
		"name": "アスカロン・D. plug・レヴィアタン",
		"quest_QuestCharacterS": 351023231,
		"priority": 704
	},
	{
		"ID": 705,
		"name": "七支刀",
		"quest_QuestCharacterS": 351051131,
		"priority": 705
	},
	{
		"ID": 706,
		"name": "アズサ",
		"quest_QuestCharacterS": 351052231,
		"priority": 706
	},
	{
		"ID": 707,
		"name": "高原の魔女 アズサ",
		"quest_QuestCharacterS": 351052131,
		"priority": 707
	},
	{
		"ID": 708,
		"name": "ライカ",
		"quest_QuestCharacterS": 352001031,
		"priority": 708
	},
	{
		"ID": 709,
		"name": "ハルカラ",
		"quest_QuestCharacterS": 356040131,
		"priority": 709
	},
	{
		"ID": 710,
		"name": "ぬりかべ",
		"quest_QuestCharacterS": 352033131,
		"priority": 710
	},
	{
		"ID": 711,
		"name": "滝夜叉姫",
		"quest_QuestCharacterS": 353038131,
		"priority": 711
	},
	{
		"ID": 712,
		"name": "アポロン・聖鎖・ラドゥエリエル",
		"quest_QuestCharacterS": 334003131,
		"priority": 712
	},
	{
		"ID": 713,
		"name": "ロンギヌス",
		"quest_QuestCharacterS": 351301131,
		"priority": 713
	},
	{
		"ID": 714,
		"name": "マサムネ",
		"quest_QuestCharacterS": 351001431,
		"priority": 714
	},
	{
		"ID": 715,
		"name": "白雪みしろ",
		"quest_QuestCharacterS": 356041131,
		"priority": 715
	},
	{
		"ID": 716,
		"name": "鬼灯わらべ",
		"quest_QuestCharacterS": 351053131,
		"priority": 716
	},
	{
		"ID": 717,
		"name": "メギド・獣刻・バロール",
		"quest_QuestCharacterS": 335006131,
		"priority": 717
	},
	{
		"ID": 718,
		"name": "ミーミル",
		"quest_QuestCharacterS": 362012131,
		"priority": 718
	},
	{
		"ID": 719,
		"name": "ティルフィング",
		"quest_QuestCharacterS": 361014431,
		"priority": 719
	}
]